Workbook

Sheet Instructions
A1: Context | B1: Consider yourself founder of PoultryCare ERP as Cloud-based ERP solution specific to poultry industry, which serves for all poultry segments like layer, broiler, breeder, broiler integration, hatchery, feedmill and processing plant. As you have experience in both technology and hand-holding exposer with poultry farm owners, use your journey of this into opportunity to address poultry farmer's business needs, pain points and problems through blogs.
A2: Role | B2: You play the role of Content marketing head to position PoultryCare ERP using organic content marketing.
A3: Format
A4: Blog | B4: , description for google SEO, blog content around 5000 words with more detailed explanation having 4 to 6 sub-headings and 4 tags. Don't mention PoltryCare ERP anywhere
A5: LinkedIn | B5: LinkedIn post as conversational format as Hook/question, insightful problem statement, solution for the problem, call-to-action for engagement. Dont include section titles in the content. All within maximum 300 words. Mention PoltryCare if possible in the content, also suggest 4 hashtags addition to #poultrycare each hash tag in small character
A6: Instagram | B6: Instagram post as conversational format as Hook/question, insightful problem statement, solution for the problem, call-to-action for engagement. Dont include section titles in the content. All within maximum 300 words. Mention PoltryCare if possible in the content, also suggest 4 hashtags addition to #poultrycare each hash tag in small character
A7: Facebook | B7: Facebook post as conversational format as Hook/question, insightful problem statement, solution for the problem, call-to-action for engagement. Dont include section titles in the content. All within maximum 300 words. Mention PoltryCare if possible in the content, also suggest 4 hashtags addition to #poultrycare each hash tag in small character
A8: Twitter | B8: Twitter post as conversational format as Hook/question, insightful problem statement, solution for the problem, call-to-action for engagement. Dont include section titles in the content. All within maximum 100 words. Mention PoltryCare if possible in the content, also suggest 4 hashtags addition to #poultrycare each hash tag in small character
A9: Reals | B9: Create script for www.narakeet.com to develop reals and shots video to highlight inventory management to match Managing Contract Broiler Farming farm inventory which generates traffic for landing page matching title. Template for video script for 30 sec, should be start with hook, highlight problem statement, give solution as pointer, end with punch. Add call to action to request PoultryCare subscription for similar tips and guides
B11: Template for video script for 30 sec, should be start with hook, highlight problem statement, give solution as pointer, end with punch. Add call to action to request PoultryCare subscription for similar tips and guides

Sheet NDP
A1: Fear | B1: PainPoints | C1: Problem | D1: Needs | E1: Desire | F1: Fantasis
A2: High Mortality | B2: Feed purchase cost | C2: data manipulation | D2: Climate change introduction | E2: Sales lifting time avoid manual interruption | F2: data activity log
A3: Supply Chain | B3: Farm supervisors visit | C3: Chick placement | D3: Feed standards | E3: Low stock alerts | F3: Lifting Bluetooth integration
A4: Invesment planning | B4: Feed over stock | C4: Medications | D4: Bodyweight taking | E4: Schedule reminders | F4: feed intent based standards
A5: Birds delivery management | B5: Multiple time placement | C5: Feed quality | D5: Farm supervisor daily visit farms | E5: Farm supervisors tracking | F5: Geo mapping locations
A6: Climate chnages | B6: Recommended feed formula | C6: Recommended age feed types | D6: Sales planning | E6: Farm to foucs | F6: Wayment integrations
A7: Data security | B7: Brooding | C7: Feed transfers | D7: Birds placement planning | E7: Body Weight comparison | F7: Supply chain tracking
B8: Farmers birds stock Management | C8: Farmers training | D8: Farmer checklist instructions | E8: Performance comparesion to plcement | F8: Maturity birds
B9: Feed nutrients | C9: Birds shortages | D9: Broiler integration | E9: Growing charge Repat Birds shoratage | F9: unpaid purchase
B10: Feed forecast | C10: Unvisited farms | D10: debugging | E10: Suppliers due amount | F10: unreceived invoices
B11: Medication schedule | C11: Mean age | D11: maturity date | E11: Customers due amount | F11: Growing Charge scheme
C12: Fcr high | D12: Farm to Focus | E12: Shed ready checklist | F12: sequence approval
C13: Body weight low | D13: Unvisited farms | E13: High mean age | F13: Fcr incentives
C14: Biosecurity | D14: Farmer performances | E14: Birds paced sizing | F14: Employee Allowance clainming
C15: High feed intake farms | D15: Farm capacity take intent birds | E15: Capacity to blow bird's placement | F15: Estimation chicks
C16: High birds placement | D16: Feed intent | E16: High mortality alert | F16: Perbird intake
C17: Employee consequences | D17: Contract farmars | E17: Temperature Monitor | F17: Recommed feed per age
C18: inter farm feed transfer | D18: Farmers education | E18: Water Intake | F18: Production cost
D19: Line run | E19: Folck tracking | F19: Cull brids
D20: Farm visit tracking | E20: EEF | F20: Rate Materix
D21: Optimum placement gap dates | E21: Farmer Grade | F21: Maintenance
D22: Breed standars | E22: Line accountability
D23: Observations
D24: Farmer Journal
D25: Branch tracking
D26: Livability
D27: Depleation

Sheet Keywords
A1: Farm | B1: Categories | C1: NDP | D1: 1st | E1: 2nd | F1: 3rd
A2: CBF Farm | B2: Fear | C2: High Mortality | D2: CBF Disease Management | E2: Act as a founder of PoultryCare ERP as Cloud-based ERP solution specific to poultry industry, which serves for all poultry segments like layer, broiler, breeder, broiler integration, hatchery, feedmill and processing plant. As you have experience in both technology and hand-holding exposer with poultry farm owners, use your journey of this into opportunity to address poultry farmer's business needs, pain points and problems through blogs. You play the role of Content marketing head to position PoultryCare ERP using organic content marketing. You Are planning to run a blog for Contract broiler farming for 50 days and educate a poultry farmers, to resolving their fear like ( High Mortality, Supply Chain(feed), Invesment planning, Birds delivery management, Climate changes, Data security ) , Pain points like ( Feed purchase cost, Farm supervisors visit, Feed over stock, Multiple time placement, Recommended feed formula, Brooding, Farmers birds stock Management, Feed nutrients, Feed forecast, Medication schedule ), and their facing a problems like (data manipulation, Chick placement, Medications, Feed quality, Recommended age feed types, Feed transfers, Farmers training, Birds shortages, Unvisited farms, Mean age , Fcr high, Body weight low, Biosecurity, High feed intake farms, High birds placement, Employee consequences, inter farm feed transfer ), And their needs to develope their farm are ( Climate change introduction, Feed standards, Bodyweight taking, Farm supervisor daily visit farms, Sales planning, Birds placement planning, Farmer checklist instructions, Broiler integration, debugging, maturity date, Farm to Focus, Unvisited farms, Farmer performances, Farm capacity take intent birds, Feed intent , Contract farmars, Farmers education, Line run, Farm visit tracking, Optimum placement gap dates, Breed standars, Observations, Farmer Journal, Branch trackin, , Livability, Depleation ) and how to desire their needs by ( Sales lifting time avoid manual interruption, Low stock alerts, Schedule reminders, Farm supervisors tracking, Farm to foucs, Body Weight comparison, Performance comparesion to plcement, Growing charge Repat Birds shoratage, Suppliers due amount, Customers due amount, Shed ready checklist, High mean age, Birds paced sizing, Capacity to blow bird's placement, High mortality alert, Temperature Monitor,Water Intake, Folck tracking, EEF, Farmer Grade, Line accountability )and how its helps to fullfill their fantasis ( Schedule based production, Indent based projection, Projection based sotck comparesion, Formula cost analysics, Yeild comparesion, Cost per kg analysics, Autom remind stock less, Lab test report ananalysics, Purchase flow tracking, inventory to production comparesion, Current stock based closing stock value, Production loss, Order managment, Moisture loss, Real time cost tracking, Order based feed delivery, Materil cost ananysics, Low stock notification, Expect feed output to actual out put comparesion, Feed production compase standard nutrients, Stage wise feed scheduling, Age wise feed recommded quanity, Cost comparesion production to production, Feed supply chain management ) give heading for 50 day to run a blog for educating poultry farmers with poultry farmers understanding tone to create more engagement Don't mention PoltryCare ERP anywhere to create more engagement.
A3: CBF Farm | B3: Fear | C3: Supply Chain(feed) | D3: inventory management
A4: CBF Farm | B4: Fear | C4: Invesment planning | D4: Farmer score based invesment
A5: CBF Farm | B5: Fear | C5: Birds delivery management | D5: Birds lifting
A6: CBF Farm | B6: Fear | C6: Climate changes | D6: Weather preparedness
A7: CBF Farm | B7: Fear | C7: Data security | D7: bio-security management
A8: CBF Farm | B8: PainPoints | C8: Feed purchase cost | D8: Feed cost analtics
A9: CBF Farm | B9: PainPoints | C9: Farm supervisors visit | D9: Regular monitoring
A10: CBF Farm | B10: PainPoints | C10: Feed over stock | D10: Feed stock management
A11: CBF Farm | B11: PainPoints | C11: Multiple time placement | D11: Birds age variation
A12: CBF Farm | B12: PainPoints | C12: Recommended feed formula | D12: Feed formula counselling
A13: CBF Farm | B13: PainPoints | C13: Brooding | D13: Brooding statergies,
A14: CBF Farm | B14: PainPoints | C14: Farmers birds stock Management | D14: Birds count tracking
... A35: CBF Farm | B35: Needs | C35: Climate change introduction | D35: Weather Guidence
A36: CBF Farm | B36: Needs | C36: Feed standards
A37: CBF Farm | B37: Needs | C37: Bodyweight taking
A38: CBF Farm | B38: Needs | C38: Farm supervisor daily visit farms
A39: CBF Farm | B39: Needs | C39: Sales planning
A40: CBF Farm | B40: Needs | C40: Birds placement planning
A41: CBF Farm | B41: Needs | C41: Farmer checklist instructions
A42: CBF Farm | B42: Needs | C42: Broiler integration
A43: CBF Farm | B43: Needs | C43: debugging
A44: CBF Farm | B44: Needs | C44: maturity date
A45: CBF Farm | B45: Needs | C45: Farm to Focus
A46: CBF Farm | B46: Needs | C46: Unvisited farms
A47: CBF Farm | B47: Needs | C47: Farmer performances
... A101: CBF Farm | B101: Fantasis | C101: Maintenance
A102: CBF Farm
A103: CBF Farm
A104: CBF Farm
A105: CBF Farm
A106: CBF Farm
A107: CBF Farm
A108: CBF Farm
A109: CBF Farm
A110: CBF Farm
A111: CBF Farm

Sheet Calender
A1: S.No | B1: Content | C1: Prompt | D1: Date | E1: Title | F1: Link | G1: medium website
A2: 1 | B2: How to Overcome High Mortality Rates in Contract Broiler Farming | C2: =CONCATENATE("Act as a founder of PoultryCare ERP as Cloud-based ERP solution specific to poultry industry, which serves for all poultry segments like layer, broiler, breeder, broiler integration, hatchery, feedmill and processing plant. As you have experience in both "&"technology and hand-holding exposer with poultry farm owners, use your journey of this into opportunity to address poultry farmer's business needs, pain points and problems through blogs. You play the role of Content marketing head to position PoultryCare"&" ERP using organic content marketing. You Are planning to run a blog for Feed Mill management and educate a poultry farmers, to resolving their", B2," give heading for run a blog for educating poultry farmers with their tone to create more engagement Write a title with SEO keywords to hook visitors to continue reading, description for google SEO,Blogs convert traffic into leads. Blogs go above and beyo"&"nd product descriptions. blog content around 3000 words with more detailed explanation having 4 to 6 sub-headings and 4 tags. give the 3 keywords, Don't mention PoltryCare ERP anywhere Content should be Farmel understanding tone to create more engagement "&"and analysis with google SEO.") -> Act as a founder of PoultryCare ERP as Cloud-based ERP solution specific to poultry industry, which serves for all poultry segments like layer, broiler, breeder, broiler integration, hatchery, feedmill and processing plant. As you have experience in both technology and hand-holding exposer with poultry farm owners, use your journey of this into opportunity to address poultry farmer's business needs, pain points and problems through blogs. You play the role of Content marketing head to position PoultryCare ERP using organic content marketing. You Are planning to run a blog for Feed Mill management and educate a poultry farmers, to resolving theirHow to Overcome High Mortality Rates in Contract Broiler Farming give heading for run a blog for educating poultry farmers with their tone to create more engagement Write a title with SEO keywords to hook visitors to continue reading, description for google SEO,Blogs convert traffic into leads. Blogs go above and beyond product descriptions. blog content around 3000 words with more detailed explanation having 4 to 6 sub-headings and 4 tags. give the 3 keywords, Don't mention PoltryCare ERP anywhere Content should be Farmel understanding tone to create more engagement and analysis with google SEO. | D2: 45540 | E2: Proven Techniques to Minimize Mortality Rates in Contract Broiler Farming | F2: https://www.poultry.care/blog/proven-techniques-to-minimize-mortality-rates-in-contract-broiler-farming
A3: 2 | B3: Feed Supply Chain Challenges in Contract Broiler Farming and How to Tackle Them Effectively | C3: =CONCATENATE("Act as a founder of PoultryCare ERP as Cloud-based ERP solution specific to poultry industry, which serves for all poultry segments like layer, broiler, breeder, broiler integration, hatchery, feedmill and processing plant. As you have experience in both "&"technology and hand-holding exposer with poultry farm owners, use your journey of this into opportunity to address poultry farmer's business needs, pain points and problems through blogs. You play the role of Content marketing head to position PoultryCare"&" ERP using organic content marketing. You Are planning to run a blog for Feed Mill management and educate a poultry farmers, to resolving their", B3," give heading for run a blog for educating poultry farmers with their tone to create more engagement Write a title with SEO keywords to hook visitors to continue reading, description for google SEO,Blogs convert traffic into leads. Blogs go above and beyo"&"nd product descriptions. blog content around 3000 words with more detailed explanation having 4 to 6 sub-headings and 4 tags. give the 3 keywords, Don't mention PoltryCare ERP anywhere Content should be Farmel understanding tone to create more engagement "&"and analysis with google SEO.") -> Act as a founder of PoultryCare ERP as Cloud-based ERP solution specific to poultry industry, which serves for all poultry segments like layer, broiler, breeder, broiler integration, hatchery, feedmill and processing plant. As you have experience in both technology and hand-holding exposer with poultry farm owners, use your journey of this into opportunity to address poultry farmer's business needs, pain points and problems through blogs. You play the role of Content marketing head to position PoultryCare ERP using organic content marketing. You Are planning to run a blog for Feed Mill management and educate a poultry farmers, to resolving theirFeed Supply Chain Challenges in Contract Broiler Farming and How to Tackle Them Effectively give heading for run a blog for educating poultry farmers with their tone to create more engagement Write a title with SEO keywords to hook visitors to continue reading, description for google SEO,Blogs convert traffic into leads. Blogs go above and beyond product descriptions. blog content around 3000 words with more detailed explanation having 4 to 6 sub-headings and 4 tags. give the 3 keywords, Don't mention PoltryCare ERP anywhere Content should be Farmel understanding tone to create more engagement and analysis with google SEO. | D3: 45542 | E3: Navigating Feed Supply Chain Challenges in Contract Broiler Farming | F3: https://www.poultry.care/blog/navigating-feed-supply-chain-challenges-in-contract-broiler-farming
A4: 3 | B4: Investment Planning for Contract Broiler Farming: Key Insights for Success | C4: =CONCATENATE("Act as a founder of PoultryCare ERP as Cloud-based ERP solution specific to poultry industry, which serves for all poultry segments like layer, broiler, breeder, broiler integration, hatchery, feedmill and processing plant. As you have experience in both "&"technology and hand-holding exposer with poultry farm owners, use your journey of this into opportunity to address poultry farmer's business needs, pain points and problems through blogs. You play the role of Content marketing head to position PoultryCare"&" ERP using organic content marketing. You Are planning to run a blog for Feed Mill management and educate a poultry farmers, to resolving their", B4," give heading for run a blog for educating poultry farmers with their tone to create more engagement Write a title with SEO keywords to hook visitors to continue reading, description for google SEO,Blogs convert traffic into leads. Blogs go above and beyo"&"nd product descriptions. blog content around 3000 words with more detailed explanation having 4 to 6 sub-headings and 4 tags. give the 3 keywords, Don't mention PoltryCare ERP anywhere Content should be Farmel understanding tone to create more engagement "&"and analysis with google SEO.") -> Act as a founder of PoultryCare ERP as Cloud-based ERP solution specific to poultry industry, which serves for all poultry segments like layer, broiler, breeder, broiler integration, hatchery, feedmill and processing plant. As you have experience in both technology and hand-holding exposer with poultry farm owners, use your journey of this into opportunity to address poultry farmer's business needs, pain points and problems through blogs. You play the role of Content marketing head to position PoultryCare ERP using organic content marketing. You Are planning to run a blog for Feed Mill management and educate a poultry farmers, to resolving theirInvestment Planning for Contract Broiler Farming: Key Insights for Success give heading for run a blog for educating poultry farmers with their tone to create more engagement Write a title with SEO keywords to hook visitors to continue reading, description for google SEO,Blogs convert traffic into leads. Blogs go above and beyond product descriptions. blog content around 3000 words with more detailed explanation having 4 to 6 sub-headings and 4 tags. give the 3 keywords, Don't mention PoltryCare ERP anywhere Content should be Farmel understanding tone to create more engagement and analysis with google SEO. | D4: 45544 | E4: Mastering Investment Planning for Contract Broiler Farming | F4: https://www.poultry.care/blog/mastering-investment-planning-for-contract-broiler-farming
A5: 4 | B5: Optimizing Birds Delivery Management in Contract Broiler Farming for Consistent Results | C5: =CONCATENATE("Act as a founder of PoultryCare ERP as Cloud-based ERP solution specific to poultry industry, which serves for all poultry segments like layer, broiler, breeder, broiler integration, hatchery, feedmill and processing plant. As you have experience in both "&"technology and hand-holding exposer with poultry farm owners, use your journey of this into opportunity to address poultry farmer's business needs, pain points and problems through blogs. You play the role of Content marketing head to position PoultryCare"&" ERP using organic content marketing. You Are planning to run a blog for Feed Mill management and educate a poultry farmers, to resolving their", B5," give heading for run a blog for educating poultry farmers with their tone to create more engagement Write a title with SEO keywords to hook visitors to continue reading, description for google SEO,Blogs convert traffic into leads. Blogs go above and beyo"&"nd product descriptions. blog content around 3000 words with more detailed explanation having 4 to 6 sub-headings and 4 tags. give the 3 keywords, Don't mention PoltryCare ERP anywhere Content should be Farmel understanding tone to create more engagement "&"and analysis with google SEO.") -> Act as a founder of PoultryCare ERP as Cloud-based ERP solution specific to poultry industry, which serves for all poultry segments like layer, broiler, breeder, broiler integration, hatchery, feedmill and processing plant. As you have experience in both technology and hand-holding exposer with poultry farm owners, use your journey of this into opportunity to address poultry farmer's business needs, pain points and problems through blogs. You play the role of Content marketing head to position PoultryCare ERP using organic content marketing. You Are planning to run a blog for Feed Mill management and educate a poultry farmers, to resolving theirOptimizing Birds Delivery Management in Contract Broiler Farming for Consistent Results give heading for run a blog for educating poultry farmers with their tone to create more engagement Write a title with SEO keywords to hook visitors to continue reading, description for google SEO,Blogs convert traffic into leads. Blogs go above and beyond product descriptions. blog content around 3000 words with more detailed explanation having 4 to 6 sub-headings and 4 tags. give the 3 keywords, Don't mention PoltryCare ERP anywhere Content should be Farmel understanding tone to create more engagement and analysis with google SEO. | D5: 45546 | E5: Optimizing Bird Delivery Management in Contract Broiler Farming for Consistent Results | F5: https://www.poultry.care/blog/optimizing-bird-delivery-management-in-contract-broiler-farming-for-consistent-results
A6: 5 | B6: Preparing Your Contract Broiler Farming Operation for Climate Change | C6: =CONCATENATE("Act as a founder of PoultryCare ERP as Cloud-based ERP solution specific to poultry industry, which serves for all poultry segments like layer, broiler, breeder, broiler integration, hatchery, feedmill and processing plant. As you have experience in both "&"technology and hand-holding exposer with poultry farm owners, use your journey of this into opportunity to address poultry farmer's business needs, pain points and problems through blogs. You play the role of Content marketing head to position PoultryCare"&" ERP using organic content marketing. You Are planning to run a blog for Feed Mill management and educate a poultry farmers, to resolving their", B6," give heading for run a blog for educating poultry farmers with their tone to create more engagement Write a title with SEO keywords to hook visitors to continue reading, description for google SEO,Blogs convert traffic into leads. Blogs go above and beyo"&"nd product descriptions. blog content around 3000 words with more detailed explanation having 4 to 6 sub-headings and 4 tags. give the 3 keywords, Don't mention PoltryCare ERP anywhere Content should be Farmel understanding tone to create more engagement "&"and analysis with google SEO.") -> Act as a founder of PoultryCare ERP as Cloud-based ERP solution specific to poultry industry, which serves for all poultry segments like layer, broiler, breeder, broiler integration, hatchery, feedmill and processing plant. As you have experience in both technology and hand-holding exposer with poultry farm owners, use your journey of this into opportunity to address poultry farmer's business needs, pain points and problems through blogs. You play the role of Content marketing head to position PoultryCare ERP using organic content marketing. You Are planning to run a blog for Feed Mill management and educate a poultry farmers, to resolving theirPreparing Your Contract Broiler Farming Operation for Climate Change give heading for run a blog for educating poultry farmers with their tone to create more engagement Write a title with SEO keywords to hook visitors to continue reading, description for google SEO,Blogs convert traffic into leads. Blogs go above and beyond product descriptions. blog content around 3000 words with more detailed explanation having 4 to 6 sub-headings and 4 tags. give the 3 keywords, Don't mention PoltryCare ERP anywhere Content should be Farmel understanding tone to create more engagement and analysis with google SEO. | D6: 45548 | E6: Preparing Your Contract Broiler Farming Operation for Climate Change | F6: https://www.poultry.care/blog/preparing-your-contract-broiler-farming-operation-for-climate-change
A7: 6 | B7: The Importance of Data Security in Contract Broiler Farming | C7: =CONCATENATE("Act as a founder of PoultryCare ERP as Cloud-based ERP solution specific to poultry industry, which serves for all poultry segments like layer, broiler, breeder, broiler integration, hatchery, feedmill and processing plant. As you have experience in both "&"technology and hand-holding exposer with poultry farm owners, use your journey of this into opportunity to address poultry farmer's business needs, pain points and problems through blogs. You play the role of Content marketing head to position PoultryCare"&" ERP using organic content marketing. You Are planning to run a blog for Feed Mill management and educate a poultry farmers, to resolving their", B7," give heading for run a blog for educating poultry farmers with their tone to create more engagement Write a title with SEO keywords to hook visitors to continue reading, description for google SEO,Blogs convert traffic into leads. Blogs go above and beyo"&"nd product descriptions. blog content around 3000 words with more detailed explanation having 4 to 6 sub-headings and 4 tags. give the 3 keywords, Don't mention PoltryCare ERP anywhere Content should be Farmel understanding tone to create more engagement "&"and analysis with google SEO.") -> Act as a founder of PoultryCare ERP as Cloud-based ERP solution specific to poultry industry, which serves for all poultry segments like layer, broiler, breeder, broiler integration, hatchery, feedmill and processing plant. As you have experience in both technology and hand-holding exposer with poultry farm owners, use your journey of this into opportunity to address poultry farmer's business needs, pain points and problems through blogs. You play the role of Content marketing head to position PoultryCare ERP using organic content marketing. You Are planning to run a blog for Feed Mill management and educate a poultry farmers, to resolving theirThe Importance of Data Security in Contract Broiler Farming give heading for run a blog for educating poultry farmers with their tone to create more engagement Write a title with SEO keywords to hook visitors to continue reading, description for google SEO,Blogs convert traffic into leads. Blogs go above and beyond product descriptions. blog content around 3000 words with more detailed explanation having 4 to 6 sub-headings and 4 tags. give the 3 keywords, Don't mention PoltryCare ERP anywhere Content should be Farmel understanding tone to create more engagement and analysis with google SEO. | D7: 45550 | E7: Why Data Security is Essential for Your Feed Mill in Poultry Farming | F7: https://www.poultry.care/blog/why-data-security-is-essential-for-your-feed-mill-in-poultry-farming
A8: 7 | B8: Managing Feed Purchase Costs to Maximize Profitability in Contract Broiler Farming | C8: =CONCATENATE("Act as a founder of PoultryCare ERP as Cloud-based ERP solution specific to poultry industry, which serves for all poultry segments like layer, broiler, breeder, broiler integration, hatchery, feedmill and processing plant. As you have experience in both "&"technology and hand-holding exposer with poultry farm owners, use your journey of this into opportunity to address poultry farmer's business needs, pain points and problems through blogs. You play the role of Content marketing head to position PoultryCare"&" ERP using organic content marketing. You Are planning to run a blog for Feed Mill management and educate a poultry farmers, to resolving their", B8," give heading for run a blog for educating poultry farmers with their tone to create more engagement Write a title with SEO keywords to hook visitors to continue reading, description for google SEO,Blogs convert traffic into leads. Blogs go above and beyo"&"nd product descriptions. blog content around 3000 words with more detailed explanation having 4 to 6 sub-headings and 4 tags. give the 3 keywords, Don't mention PoltryCare ERP anywhere Content should be Farmel understanding tone to create more engagement "&"and analysis with google SEO.") -> Act as a founder of PoultryCare ERP as Cloud-based ERP solution specific to poultry industry, which serves for all poultry segments like layer, broiler, breeder, broiler integration, hatchery, feedmill and processing plant. As you have experience in both technology and hand-holding exposer with poultry farm owners, use your journey of this into opportunity to address poultry farmer's business needs, pain points and problems through blogs. You play the role of Content marketing head to position PoultryCare ERP using organic content marketing. You Are planning to run a blog for Feed Mill management and educate a poultry farmers, to resolving theirManaging Feed Purchase Costs to Maximize Profitability in Contract Broiler Farming give heading for run a blog for educating poultry farmers with their tone to create more engagement Write a title with SEO keywords to hook visitors to continue reading, description for google SEO,Blogs convert traffic into leads. Blogs go above and beyond product descriptions. blog content around 3000 words with more detailed explanation having 4 to 6 sub-headings and 4 tags. give the 3 keywords, Don't mention PoltryCare ERP anywhere Content should be Farmel understanding tone to create more engagement and analysis with google SEO. | D8: 45552 | E8: How to Cut Feed Costs and Boost Profits in Broiler Farming | F8: https://www.poultry.care/blog/how-to-cut-feed-costs-and-boost-profits-in-broiler-farming
A9: 8 | B9: The Value of Regular Farm Supervisor Visits for Contract Broiler Farming | C9: =CONCATENATE("Act as a founder of PoultryCare ERP as Cloud-based ERP solution specific to poultry industry, which serves for all poultry segments like layer, broiler, breeder, broiler integration, hatchery, feedmill and processing plant. As you have experience in both "&"technology and hand-holding exposer with poultry farm owners, use your journey of this into opportunity to address poultry farmer's business needs, pain points and problems through blogs. You play the role of Content marketing head to position PoultryCare"&" ERP using organic content marketing. You Are planning to run a blog for Feed Mill management and educate a poultry farmers, to resolving their", B9," give heading for run a blog for educating poultry farmers with their tone to create more engagement Write a title with SEO keywords to hook visitors to continue reading, description for google SEO,Blogs convert traffic into leads. Blogs go above and beyo"&"nd product descriptions. blog content around 3000 words with more detailed explanation having 4 to 6 sub-headings and 4 tags. give the 3 keywords, Don't mention PoltryCare ERP anywhere Content should be Farmel understanding tone to create more engagement "&"and analysis with google SEO.") -> Act as a founder of PoultryCare ERP as Cloud-based ERP solution specific to poultry industry, which serves for all poultry segments like layer, broiler, breeder, broiler integration, hatchery, feedmill and processing plant. As you have experience in both technology and hand-holding exposer with poultry farm owners, use your journey of this into opportunity to address poultry farmer's business needs, pain points and problems through blogs. You play the role of Content marketing head to position PoultryCare ERP using organic content marketing. You Are planning to run a blog for Feed Mill management and educate a poultry farmers, to resolving theirThe Value of Regular Farm Supervisor Visits for Contract Broiler Farming give heading for run a blog for educating poultry farmers with their tone to create more engagement Write a title with SEO keywords to hook visitors to continue reading, description for google SEO,Blogs convert traffic into leads. Blogs go above and beyond product descriptions. blog content around 3000 words with more detailed explanation having 4 to 6 sub-headings and 4 tags. give the 3 keywords, Don't mention PoltryCare ERP anywhere Content should be Farmel understanding tone to create more engagement and analysis with google SEO. | D9: 45554 | E9: Why Regular Farm Supervisor Visits Are Key to Success in Contract Broiler Farming | F9: https://www.poultry.care/blog/why-regular-farm-supervisor-visits-are-key-to-success-in-contract-broiler-farming
A10: 9 | B10: How to Prevent Overstocking Feed on Your Contract Broiler Farm | C10: =CONCATENATE("Act as a founder of PoultryCare ERP as Cloud-based ERP solution specific to poultry industry, which serves for all poultry segments like layer, broiler, breeder, broiler integration, hatchery, feedmill and processing plant. As you have experience in both "&"technology and hand-holding exposer with poultry farm owners, use your journey of this into opportunity to address poultry farmer's business needs, pain points and problems through blogs. You play the role of Content marketing head to position PoultryCare"&" ERP using organic content marketing. You Are planning to run a blog for Feed Mill management and educate a poultry farmers, to resolving their", B10," give heading for run a blog for educating poultry farmers with their tone to create more engagement Write a title with SEO keywords to hook visitors to continue reading, description for google SEO,Blogs convert traffic into leads. Blogs go above and beyo"&"nd product descriptions. blog content around 3000 words with more detailed explanation having 4 to 6 sub-headings and 4 tags. give the 3 keywords, Don't mention PoltryCare ERP anywhere Content should be Farmel understanding tone to create more engagement "&"and analysis with google SEO.") -> Act as a founder of PoultryCare ERP as Cloud-based ERP solution specific to poultry industry, which serves for all poultry segments like layer, broiler, breeder, broiler integration, hatchery, feedmill and processing plant. As you have experience in both technology and hand-holding exposer with poultry farm owners, use your journey of this into opportunity to address poultry farmer's business needs, pain points and problems through blogs. You play the role of Content marketing head to position PoultryCare ERP using organic content marketing. You Are planning to run a blog for Feed Mill management and educate a poultry farmers, to resolving theirHow to Prevent Overstocking Feed on Your Contract Broiler Farm give heading for run a blog for educating poultry farmers with their tone to create more engagement Write a title with SEO keywords to hook visitors to continue reading, description for google SEO,Blogs convert traffic into leads. Blogs go above and beyond product descriptions. blog content around 3000 words with more detailed explanation having 4 to 6 sub-headings and 4 tags. give the 3 keywords, Don't mention PoltryCare ERP anywhere Content should be Farmel understanding tone to create more engagement and analysis with google SEO. | D10: 45556 | E10: Effective Strategies to Prevent Overstocking Feed on Your Contract Broiler Farm | F10: https://www.poultry.care/blog/effective-strategies-to-prevent-overstocking-feed-on-your-contract-broiler-farm
A11: 10 | B11: Managing Multiple Chick Placements with Efficiency in Contract Broiler Farming | C11: =CONCATENATE("Act as a founder of PoultryCare ERP as Cloud-based ERP solution specific to poultry industry, which serves for all poultry segments like layer, broiler, breeder, broiler integration, hatchery, feedmill and processing plant. As you have experience in both "&"technology and hand-holding exposer with poultry farm owners, use your journey of this into opportunity to address poultry farmer's business needs, pain points and problems through blogs. You play the role of Content marketing head to position PoultryCare"&" ERP using organic content marketing. You Are planning to run a blog for Feed Mill management and educate a poultry farmers, to resolving their", B11," give heading for run a blog for educating poultry farmers with their tone to create more engagement Write a title with SEO keywords to hook visitors to continue reading, description for google SEO,Blogs convert traffic into leads. Blogs go above and beyo"&"nd product descriptions. blog content around 3000 words with more detailed explanation having 4 to 6 sub-headings and 4 tags. give the 3 keywords, Don't mention PoltryCare ERP anywhere Content should be Farmel understanding tone to create more engagement "&"and analysis with google SEO.") -> Act as a founder of PoultryCare ERP as Cloud-based ERP solution specific to poultry industry, which serves for all poultry segments like layer, broiler, breeder, broiler integration, hatchery, feedmill and processing plant. As you have experience in both technology and hand-holding exposer with poultry farm owners, use your journey of this into opportunity to address poultry farmer's business needs, pain points and problems through blogs. You play the role of Content marketing head to position PoultryCare ERP using organic content marketing. You Are planning to run a blog for Feed Mill management and educate a poultry farmers, to resolving theirManaging Multiple Chick Placements with Efficiency in Contract Broiler Farming give heading for run a blog for educating poultry farmers with their tone to create more engagement Write a title with SEO keywords to hook visitors to continue reading, description for google SEO,Blogs convert traffic into leads. Blogs go above and beyond product descriptions. blog content around 3000 words with more detailed explanation having 4 to 6 sub-headings and 4 tags. give the 3 keywords, Don't mention PoltryCare ERP anywhere Content should be Farmel understanding tone to create more engagement and analysis with google SEO. | D11: 45558 | E11: How to Efficiently Manage Multiple Chick Placements in Contract Broiler Farming | F11: https://www.poultry.care/blog/how-to-efficiently-manage-multiple-chick-placements-in-contract-broiler-farming
A12: 11 | B12: Understanding and Implementing the Recommended Feed Formula in Contract Broiler Farming | C12: =CONCATENATE("Act as a founder of PoultryCare ERP as Cloud-based ERP solution specific to poultry industry, which serves for all poultry segments like layer, broiler, breeder, broiler integration, hatchery, feedmill and processing plant. As you have experience in both "&"technology and hand-holding exposer with poultry farm owners, use your journey of this into opportunity to address poultry farmer's business needs, pain points and problems through blogs. You play the role of Content marketing head to position PoultryCare"&" ERP using organic content marketing. You Are planning to run a blog for Feed Mill management and educate a poultry farmers, to resolving their", B12," give heading for run a blog for educating poultry farmers with their tone to create more engagement Write a title with SEO keywords to hook visitors to continue reading, description for google SEO,Blogs convert traffic into leads. Blogs go above and beyo"&"nd product descriptions. blog content around 3000 words with more detailed explanation having 4 to 6 sub-headings and 4 tags. give the 3 keywords, Don't mention PoltryCare ERP anywhere Content should be Farmel understanding tone to create more engagement "&"and analysis with google SEO.") -> Act as a founder of PoultryCare ERP as Cloud-based ERP solution specific to poultry industry, which serves for all poultry segments like layer, broiler, breeder, broiler integration, hatchery, feedmill and processing plant. As you have experience in both technology and hand-holding exposer with poultry farm owners, use your journey of this into opportunity to address poultry farmer's business needs, pain points and problems through blogs. You play the role of Content marketing head to position PoultryCare ERP using organic content marketing. You Are planning to run a blog for Feed Mill management and educate a poultry farmers, to resolving theirUnderstanding and Implementing the Recommended Feed Formula in Contract Broiler Farming give heading for run a blog for educating poultry farmers with their tone to create more engagement Write a title with SEO keywords to hook visitors to continue reading, description for google SEO,Blogs convert traffic into leads. Blogs go above and beyond product descriptions. blog content around 3000 words with more detailed explanation having 4 to 6 sub-headings and 4 tags. give the 3 keywords, Don't mention PoltryCare ERP anywhere Content should be Farmel understanding tone to create more engagement and analysis with google SEO. | D12: 45560 | E12: Mastering the Use of Recommended Feed Formulas in Contract Broiler Farming | F12: https://www.poultry.care/blog/mastering-the-use-of-recommended-feed-formulas-in-contract-broiler-farming
A13: 12 | B13: Brooding Best Practices to Ensure Healthy Chick Development in Contract Broiler Farming | C13: =CONCATENATE("Act as a founder of PoultryCare ERP as Cloud-based ERP solution specific to poultry industry, which serves for all poultry segments like layer, broiler, breeder, broiler integration, hatchery, feedmill and processing plant. As you have experience in both "&"technology and hand-holding exposer with poultry farm owners, use your journey of this into opportunity to address poultry farmer's business needs, pain points and problems through blogs. You play the role of Content marketing head to position PoultryCare"&" ERP using organic content marketing. You Are planning to run a blog for Feed Mill management and educate a poultry farmers, to resolving their", B13," give heading for run a blog for educating poultry farmers with their tone to create more engagement Write a title with SEO keywords to hook visitors to continue reading, description for google SEO,Blogs convert traffic into leads. Blogs go above and beyo"&"nd product descriptions. blog content around 3000 words with more detailed explanation having 4 to 6 sub-headings and 4 tags. give the 3 keywords, Don't mention PoltryCare ERP anywhere Content should be Farmel understanding tone to create more engagement "&"and analysis with google SEO.") -> Act as a founder of PoultryCare ERP as Cloud-based ERP solution specific to poultry industry, which serves for all poultry segments like layer, broiler, breeder, broiler integration, hatchery, feedmill and processing plant. As you have experience in both technology and hand-holding exposer with poultry farm owners, use your journey of this into opportunity to address poultry farmer's business needs, pain points and problems through blogs. You play the role of Content marketing head to position PoultryCare ERP using organic content marketing. You Are planning to run a blog for Feed Mill management and educate a poultry farmers, to resolving theirBrooding Best Practices to Ensure Healthy Chick Development in Contract Broiler Farming give heading for run a blog for educating poultry farmers with their tone to create more engagement Write a title with SEO keywords to hook visitors to continue reading, description for google SEO,Blogs convert traffic into leads. Blogs go above and beyond product descriptions. blog content around 3000 words with more detailed explanation having 4 to 6 sub-headings and 4 tags. give the 3 keywords, Don't mention PoltryCare ERP anywhere Content should be Farmel understanding tone to create more engagement and analysis with google SEO. | D13: 45562 | E13: Brooding Techniques Every Poultry Farmer Should Know for Strong and Healthy Chicks | F13: https://www.poultry.care/blog/brooding-techniques-every-poultry-farmer-should-know-for-strong-and-healthy-chicks
A14: 13 | B14: Effectively Managing Bird Stock in Contract Broiler Farming to Avoid Shortages | C14: =CONCATENATE("Act as a founder of PoultryCare ERP as Cloud-based ERP solution specific to poultry industry, which serves for all poultry segments like layer, broiler, breeder, broiler integration, hatchery, feedmill and processing plant. As you have experience in both "&"technology and hand-holding exposer with poultry farm owners, use your journey of this into opportunity to address poultry farmer's business needs, pain points and problems through blogs. You play the role of Content marketing head to position PoultryCare"&" ERP using organic content marketing. You Are planning to run a blog for Feed Mill management and educate a poultry farmers, to resolving their", B14," give heading for run a blog for educating poultry farmers with their tone to create more engagement Write a title with SEO keywords to hook visitors to continue reading, description for google SEO,Blogs convert traffic into leads. Blogs go above and beyo"&"nd product descriptions. blog content around 1000 words with more detailed explanation having 4 to 6 sub-headings and 4 tags. give the 3 keywords, Don't mention PoltryCare ERP anywhere Content should be Farmel understanding tone to create more engagement "&"and analysis with google SEO.") -> Act as a founder of PoultryCare ERP as Cloud-based ERP solution specific to poultry industry, which serves for all poultry segments like layer, broiler, breeder, broiler integration, hatchery, feedmill and processing plant. As you have experience in both technology and hand-holding exposer with poultry farm owners, use your journey of this into opportunity to address poultry farmer's business needs, pain points and problems through blogs. You play the role of Content marketing head to position PoultryCare ERP using organic content marketing. You Are planning to run a blog for Feed Mill management and educate a poultry farmers, to resolving theirEffectively Managing Bird Stock in Contract Broiler Farming to Avoid Shortages give heading for run a blog for educating poultry farmers with their tone to create more engagement Write a title with SEO keywords to hook visitors to continue reading, description for google SEO,Blogs convert traffic into leads. Blogs go above and beyond product descriptions. blog content around 1000 words with more detailed explanation having 4 to 6 sub-headings and 4 tags. give the 3 keywords, Don't mention PoltryCare ERP anywhere Content should be Farmel understanding tone to create more engagement and analysis with google SEO. | D14: 45564 | E14: Smart Bird Stock Management for Contract Broiler Farmers to Avoid Supply Gaps | F14: https://www.poultry.care/blog/smart-bird-stock-management-for-contract-broiler-farmers-to-avoid-supply-gaps
A15: 14 | B15: Feed Nutrients Management for Optimal Growth and Health in Contract Broiler Farming | C15: =CONCATENATE("Act as a founder of PoultryCare ERP as Cloud-based ERP solution specific to poultry industry, which serves for all poultry segments like layer, broiler, breeder, broiler integration, hatchery, feedmill and processing plant. As you have experience in both "&"technology and hand-holding exposer with poultry farm owners, use your journey of this into opportunity to address poultry farmer's business needs, pain points and problems through blogs. You play the role of Content marketing head to position PoultryCare"&" ERP using organic content marketing. You Are planning to run a blog for Feed Mill management and educate a poultry farmers, to resolving their", B15," give heading for run a blog for educating poultry farmers with their tone to create more engagement Write a title with SEO keywords to hook visitors to continue reading, description for google SEO,Blogs convert traffic into leads. Blogs go above and beyo"&"nd product descriptions. blog content around 1000 words with more detailed explanation having 4 to 6 sub-headings and 4 tags. give the 3 keywords, Don't mention PoltryCare ERP anywhere Content should be Farmel understanding tone to create more engagement "&"and analysis with google SEO.") -> Act as a founder of PoultryCare ERP as Cloud-based ERP solution specific to poultry industry, which serves for all poultry segments like layer, broiler, breeder, broiler integration, hatchery, feedmill and processing plant. As you have experience in both technology and hand-holding exposer with poultry farm owners, use your journey of this into opportunity to address poultry farmer's business needs, pain points and problems through blogs. You play the role of Content marketing head to position PoultryCare ERP using organic content marketing. You Are planning to run a blog for Feed Mill management and educate a poultry farmers, to resolving theirFeed Nutrients Management for Optimal Growth and Health in Contract Broiler Farming give heading for run a blog for educating poultry farmers with their tone to create more engagement Write a title with SEO keywords to hook visitors to continue reading, description for google SEO,Blogs convert traffic into leads. Blogs go above and beyond product descriptions. blog content around 1000 words with more detailed explanation having 4 to 6 sub-headings and 4 tags. give the 3 keywords, Don't mention PoltryCare ERP anywhere Content should be Farmel understanding tone to create more engagement and analysis with google SEO. | D15: 45566 | E15: Optimizing Feed Nutrients for Healthy and Rapid Growth in Contract Broiler Farming | F15: https://www.poultry.care/blog/optimizing-feed-nutrients-for-healthy-and-rapid-growth-in-contract-broiler-farming
A16: 15 | B16: How to Forecast Feed Needs in Contract Broiler Farming | C16: =CONCATENATE("Act as a founder of PoultryCare ERP as Cloud-based ERP solution specific to poultry industry, which serves for all poultry segments like layer, broiler, breeder, broiler integration, hatchery, feedmill and processing plant. As you have experience in both "&"technology and hand-holding exposer with poultry farm owners, use your journey of this into opportunity to address poultry farmer's business needs, pain points and problems through blogs. You play the role of Content marketing head to position PoultryCare"&" ERP using organic content marketing. You Are planning to run a blog for Feed Mill management and educate a poultry farmers, to resolving their", B16," give heading for run a blog for educating poultry farmers with their tone to create more engagement Write a title with SEO keywords to hook visitors to continue reading, description for google SEO,Blogs convert traffic into leads. Blogs go above and beyo"&"nd product descriptions. blog content around 1000 words with more detailed explanation having 4 to 6 sub-headings and 4 tags. give the 3 keywords, Don't mention PoltryCare ERP anywhere Content should be Farmel understanding tone to create more engagement "&"and analysis with google SEO.") -> Act as a founder of PoultryCare ERP as Cloud-based ERP solution specific to poultry industry, which serves for all poultry segments like layer, broiler, breeder, broiler integration, hatchery, feedmill and processing plant. As you have experience in both technology and hand-holding exposer with poultry farm owners, use your journey of this into opportunity to address poultry farmer's business needs, pain points and problems through blogs. You play the role of Content marketing head to position PoultryCare ERP using organic content marketing. You Are planning to run a blog for Feed Mill management and educate a poultry farmers, to resolving theirHow to Forecast Feed Needs in Contract Broiler Farming give heading for run a blog for educating poultry farmers with their tone to create more engagement Write a title with SEO keywords to hook visitors to continue reading, description for google SEO,Blogs convert traffic into leads. Blogs go above and beyond product descriptions. blog content around 1000 words with more detailed explanation having 4 to 6 sub-headings and 4 tags. give the 3 keywords, Don't mention PoltryCare ERP anywhere Content should be Farmel understanding tone to create more engagement and analysis with google SEO. | D16: 45568 | E16: Accurately Forecasting Feed Needs for Contract Broiler Farms to Maximize Profits | F16: https://www.poultry.care/blog/accurately-forecasting-feed-needs-for-contract-broiler-farms-to-maximize-profits
A17: 16 | B17: Creating and Following an Effective Medication Schedule in Contract Broiler Farming | C17: =CONCATENATE("Act as a founder of PoultryCare ERP as Cloud-based ERP solution specific to poultry industry, which serves for all poultry segments like layer, broiler, breeder, broiler integration, hatchery, feedmill and processing plant. As you have experience in both "&"technology and hand-holding exposer with poultry farm owners, use your journey of this into opportunity to address poultry farmer's business needs, pain points and problems through blogs. You play the role of Content marketing head to position PoultryCare"&" ERP using organic content marketing. You Are planning to run a blog for Feed Mill management and educate a poultry farmers, to resolving their", B17," give heading for run a blog for educating poultry farmers with their tone to create more engagement Write a title with SEO keywords to hook visitors to continue reading, description for google SEO,Blogs convert traffic into leads. Blogs go above and beyo"&"nd product descriptions. blog content around 1000 words with more detailed explanation having 4 to 6 sub-headings and 4 tags. give the 3 keywords, Don't mention PoltryCare ERP anywhere Content should be Farmel understanding tone to create more engagement "&"and analysis with google SEO.") -> Act as a founder of PoultryCare ERP as Cloud-based ERP solution specific to poultry industry, which serves for all poultry segments like layer, broiler, breeder, broiler integration, hatchery, feedmill and processing plant. As you have experience in both technology and hand-holding exposer with poultry farm owners, use your journey of this into opportunity to address poultry farmer's business needs, pain points and problems through blogs. You play the role of Content marketing head to position PoultryCare ERP using organic content marketing. You Are planning to run a blog for Feed Mill management and educate a poultry farmers, to resolving theirCreating and Following an Effective Medication Schedule in Contract Broiler Farming give heading for run a blog for educating poultry farmers with their tone to create more engagement Write a title with SEO keywords to hook visitors to continue reading, description for google SEO,Blogs convert traffic into leads. Blogs go above and beyond product descriptions. blog content around 1000 words with more detailed explanation having 4 to 6 sub-headings and 4 tags. give the 3 keywords, Don't mention PoltryCare ERP anywhere Content should be Farmel understanding tone to create more engagement and analysis with google SEO. | D17: 45570 | E17: How to Create and Follow an Effective Medication Schedule in Contract Broiler Farming | F17: https://www.poultry.care/blog/how-to-create-and-follow-an-effective-medication-schedule-in-contract-broiler-farming
A18: 17 | B18: Avoiding Data Manipulation in Contract Broiler Farming | C18: =CONCATENATE("Act as a founder of PoultryCare ERP as Cloud-based ERP solution specific to poultry industry, which serves for all poultry segments like layer, broiler, breeder, broiler integration, hatchery, feedmill and processing plant. As you have experience in both "&"technology and hand-holding exposer with poultry farm owners, use your journey of this into opportunity to address poultry farmer's business needs, pain points and problems through blogs. You play the role of Content marketing head to position PoultryCare"&" ERP using organic content marketing. You Are planning to run a blog for Feed Mill management and educate a poultry farmers, to resolving their", B18," give heading for run a blog for educating poultry farmers with their tone to create more engagement Write a title with SEO keywords to hook visitors to continue reading, description for google SEO,Blogs convert traffic into leads. Blogs go above and beyo"&"nd product descriptions. blog content around 1000 words with more detailed explanation having 4 to 6 sub-headings and 4 tags. give the 3 keywords, Don't mention PoltryCare ERP anywhere Content should be Farmel understanding tone to create more engagement "&"and analysis with google SEO.") -> Act as a founder of PoultryCare ERP as Cloud-based ERP solution specific to poultry industry, which serves for all poultry segments like layer, broiler, breeder, broiler integration, hatchery, feedmill and processing plant. As you have experience in both technology and hand-holding exposer with poultry farm owners, use your journey of this into opportunity to address poultry farmer's business needs, pain points and problems through blogs. You play the role of Content marketing head to position PoultryCare ERP using organic content marketing. You Are planning to run a blog for Feed Mill management and educate a poultry farmers, to resolving theirAvoiding Data Manipulation in Contract Broiler Farming give heading for run a blog for educating poultry farmers with their tone to create more engagement Write a title with SEO keywords to hook visitors to continue reading, description for google SEO,Blogs convert traffic into leads. Blogs go above and beyond product descriptions. blog content around 1000 words with more detailed explanation having 4 to 6 sub-headings and 4 tags. give the 3 keywords, Don't mention PoltryCare ERP anywhere Content should be Farmel understanding tone to create more engagement and analysis with google SEO. | D18: 45572 | E18: How to Prevent Data Manipulation in Contract Broiler Farming for Better Results | F18: https://www.poultry.care/blog/how-to-prevent-data-manipulation-in-contract-broiler-farming-for-better-results
A19: 18 | B19: Proper Chick Placement for Improved Growth in Contract Broiler Farming | C19: =CONCATENATE("Act as a founder of PoultryCare ERP as Cloud-based ERP solution specific to poultry industry, which serves for all poultry segments like layer, broiler, breeder, broiler integration, hatchery, feedmill and processing plant. As you have experience in both "&"technology and hand-holding exposer with poultry farm owners, use your journey of this into opportunity to address poultry farmer's business needs, pain points and problems through blogs. You play the role of Content marketing head to position PoultryCare"&" ERP using organic content marketing. You Are planning to run a blog for Feed Mill management and educate a poultry farmers, to resolving their", B19," give heading for run a blog for educating poultry farmers with their tone to create more engagement Write a title with SEO keywords to hook visitors to continue reading, description for google SEO,Blogs convert traffic into leads. Blogs go above and beyo"&"nd product descriptions. blog content around 1000 words with more detailed explanation having 4 to 6 sub-headings and 4 tags. give the 3 keywords, Don't mention PoltryCare ERP anywhere Content should be Farmel understanding tone to create more engagement "&"and analysis with google SEO.") -> Act as a founder of PoultryCare ERP as Cloud-based ERP solution specific to poultry industry, which serves for all poultry segments like layer, broiler, breeder, broiler integration, hatchery, feedmill and processing plant. As you have experience in both technology and hand-holding exposer with poultry farm owners, use your journey of this into opportunity to address poultry farmer's business needs, pain points and problems through blogs. You play the role of Content marketing head to position PoultryCare ERP using organic content marketing. You Are planning to run a blog for Feed Mill management and educate a poultry farmers, to resolving theirProper Chick Placement for Improved Growth in Contract Broiler Farming give heading for run a blog for educating poultry farmers with their tone to create more engagement Write a title with SEO keywords to hook visitors to continue reading, description for google SEO,Blogs convert traffic into leads. Blogs go above and beyond product descriptions. blog content around 1000 words with more detailed explanation having 4 to 6 sub-headings and 4 tags. give the 3 keywords, Don't mention PoltryCare ERP anywhere Content should be Farmel understanding tone to create more engagement and analysis with google SEO. | D19: 45574 | E19: Simple Chick Placement Tips for Better Growth in Contract Broiler Farming | F19: https://www.poultry.care/blog/simple-chick-placement-tips-for-better-growth-in-contract-broiler-farming
A20: 19 | B20: Ensuring High-Quality Feed for Better Bird Health in Contract Broiler Farming | C20: =CONCATENATE("Act as a founder of PoultryCare ERP as Cloud-based ERP solution specific to poultry industry, which serves for all poultry segments like layer, broiler, breeder, broiler integration, hatchery, feedmill and processing plant. As you have experience in both "&"technology and hand-holding exposer with poultry farm owners, use your journey of this into opportunity to address poultry farmer's business needs, pain points and problems through blogs. You play the role of Content marketing head to position PoultryCare"&" ERP using organic content marketing. You Are planning to run a blog for Feed Mill management and educate a poultry farmers, to resolving their", B20," give heading for run a blog for educating poultry farmers with their tone to create more engagement Write a title with SEO keywords to hook visitors to continue reading, description for google SEO,Blogs convert traffic into leads. Blogs go above and beyo"&"nd product descriptions. blog content around 1000 words with more detailed explanation having 4 to 6 sub-headings and 4 tags. give the 3 keywords, Don't mention PoltryCare ERP anywhere Content should be Farmel understanding tone to create more engagement "&"and analysis with google SEO.") -> Act as a founder of PoultryCare ERP as Cloud-based ERP solution specific to poultry industry, which serves for all poultry segments like layer, broiler, breeder, broiler integration, hatchery, feedmill and processing plant. As you have experience in both technology and hand-holding exposer with poultry farm owners, use your journey of this into opportunity to address poultry farmer's business needs, pain points and problems through blogs. You play the role of Content marketing head to position PoultryCare ERP using organic content marketing. You Are planning to run a blog for Feed Mill management and educate a poultry farmers, to resolving theirEnsuring High-Quality Feed for Better Bird Health in Contract Broiler Farming give heading for run a blog for educating poultry farmers with their tone to create more engagement Write a title with SEO keywords to hook visitors to continue reading, description for google SEO,Blogs convert traffic into leads. Blogs go above and beyond product descriptions. blog content around 1000 words with more detailed explanation having 4 to 6 sub-headings and 4 tags. give the 3 keywords, Don't mention PoltryCare ERP anywhere Content should be Farmel understanding tone to create more engagement and analysis with google SEO. | D20: 45576 | E20: How to Ensure High-Quality Feed for Healthier Birds in Contract Broiler Farming | F20: https://www.poultry.care/blog/how-to-ensure-high-quality-feed-for-healthier-birds-in-contract-broiler-farming
A21: 20 | B21: Matching Feed Types with Recommended Age Stages in Contract Broiler Farming | C21: =CONCATENATE("Act as a founder of PoultryCare ERP as Cloud-based ERP solution specific to poultry industry, which serves for all poultry segments like layer, broiler, breeder, broiler integration, hatchery, feedmill and processing plant. As you have experience in both "&"technology and hand-holding exposer with poultry farm owners, use your journey of this into opportunity to address poultry farmer's business needs, pain points and problems through blogs. You play the role of Content marketing head to position PoultryCare"&" ERP using organic content marketing. You Are planning to run a blog for Feed Mill management and educate a poultry farmers, to resolving their", B21," give heading for run a blog for educating poultry farmers with their tone to create more engagement Write a title with SEO keywords to hook visitors to continue reading, description for google SEO,Blogs convert traffic into leads. Blogs go above and beyo"&"nd product descriptions. blog content around 1000 words with more detailed explanation having 4 to 6 sub-headings and 4 tags. give the 3 keywords, Don't mention PoltryCare ERP anywhere Content should be Farmel understanding tone to create more engagement "&"and analysis with google SEO.") -> Act as a founder of PoultryCare ERP as Cloud-based ERP solution specific to poultry industry, which serves for all poultry segments like layer, broiler, breeder, broiler integration, hatchery, feedmill and processing plant. As you have experience in both technology and hand-holding exposer with poultry farm owners, use your journey of this into opportunity to address poultry farmer's business needs, pain points and problems through blogs. You play the role of Content marketing head to position PoultryCare ERP using organic content marketing. You Are planning to run a blog for Feed Mill management and educate a poultry farmers, to resolving theirMatching Feed Types with Recommended Age Stages in Contract Broiler Farming give heading for run a blog for educating poultry farmers with their tone to create more engagement Write a title with SEO keywords to hook visitors to continue reading, description for google SEO,Blogs convert traffic into leads. Blogs go above and beyond product descriptions. blog content around 1000 words with more detailed explanation having 4 to 6 sub-headings and 4 tags. give the 3 keywords, Don't mention PoltryCare ERP anywhere Content should be Farmel understanding tone to create more engagement and analysis with google SEO. | D21: 45578 | E21: How to Match Feed Types with Age Stages for Healthy Broiler Growth in Contract Farming | F21: https://www.poultry.care/blog/how-to-match-feed-types-with-age-stages-for-healthy-broiler-growth-in-contract-farming
A22: 21 | B22: How to Optimize Feed Transfers in Contract Broiler Farming | C22: =CONCATENATE("Act as a founder of PoultryCare ERP as Cloud-based ERP solution specific to poultry industry, which serves for all poultry segments like layer, broiler, breeder, broiler integration, hatchery, feedmill and processing plant. As you have experience in both "&"technology and hand-holding exposer with poultry farm owners, use your journey of this into opportunity to address poultry farmer's business needs, pain points and problems through blogs. You play the role of Content marketing head to position PoultryCare"&" ERP using organic content marketing. You Are planning to run a blog for Feed Mill management and educate a poultry farmers, to resolving their", B22," give heading for run a blog for educating poultry farmers with their tone to create more engagement Write a title with SEO keywords to hook visitors to continue reading, description for google SEO,Blogs convert traffic into leads. Blogs go above and beyo"&"nd product descriptions. blog content around 1000 words with more detailed explanation having 4 to 6 sub-headings and 4 tags. give the 3 keywords, Don't mention PoltryCare ERP anywhere Content should be Farmel understanding tone to create more engagement "&"and analysis with google SEO.") -> Act as a founder of PoultryCare ERP as Cloud-based ERP solution specific to poultry industry, which serves for all poultry segments like layer, broiler, breeder, broiler integration, hatchery, feedmill and processing plant. As you have experience in both technology and hand-holding exposer with poultry farm owners, use your journey of this into opportunity to address poultry farmer's business needs, pain points and problems through blogs. You play the role of Content marketing head to position PoultryCare ERP using organic content marketing. You Are planning to run a blog for Feed Mill management and educate a poultry farmers, to resolving theirHow to Optimize Feed Transfers in Contract Broiler Farming give heading for run a blog for educating poultry farmers with their tone to create more engagement Write a title with SEO keywords to hook visitors to continue reading, description for google SEO,Blogs convert traffic into leads. Blogs go above and beyond product descriptions. blog content around 1000 words with more detailed explanation having 4 to 6 sub-headings and 4 tags. give the 3 keywords, Don't mention PoltryCare ERP anywhere Content should be Farmel understanding tone to create more engagement and analysis with google SEO. | D22: 45712 | F22: https://www.poultry.care/blog/how-to-optimize-feed-transfers-in-contract-broiler-farming
A23: 22 | B23: Training Farmers in Modern Contract Broiler Farming Practices | C23: =CONCATENATE("Act as a founder of PoultryCare ERP as Cloud-based ERP solution specific to poultry industry, which serves for all poultry segments like layer, broiler, breeder, broiler integration, hatchery, feedmill and processing plant. As you have experience in both "&"technology and hand-holding exposer with poultry farm owners, use your journey of this into opportunity to address poultry farmer's business needs, pain points and problems through blogs. You play the role of Content marketing head to position PoultryCare"&" ERP using organic content marketing. You Are planning to run a blog for Feed Mill management and educate a poultry farmers, to resolving their", B23," give heading for run a blog for educating poultry farmers with their tone to create more engagement Write a title with SEO keywords to hook visitors to continue reading, description for google SEO,Blogs convert traffic into leads. Blogs go above and beyo"&"nd product descriptions. blog content around 1000 words with more detailed explanation having 4 to 6 sub-headings and 4 tags. give the 3 keywords, Don't mention PoltryCare ERP anywhere Content should be Farmel understanding tone to create more engagement "&"and analysis with google SEO this only for large broiler integrators.") -> Act as a founder of PoultryCare ERP as Cloud-based ERP solution specific to poultry industry, which serves for all poultry segments like layer, broiler, breeder, broiler integration, hatchery, feedmill and processing plant. As you have experience in both technology and hand-holding exposer with poultry farm owners, use your journey of this into opportunity to address poultry farmer's business needs, pain points and problems through blogs. You play the role of Content marketing head to position PoultryCare ERP using organic content marketing. You Are planning to run a blog for Feed Mill management and educate a poultry farmers, to resolving theirTraining Farmers in Modern Contract Broiler Farming Practices give heading for run a blog for educating poultry farmers with their tone to create more engagement Write a title with SEO keywords to hook visitors to continue reading, description for google SEO,Blogs convert traffic into leads. Blogs go above and beyond product descriptions. blog content around 1000 words with more detailed explanation having 4 to 6 sub-headings and 4 tags. give the 3 keywords, Don't mention PoltryCare ERP anywhere Content should be Farmel understanding tone to create more engagement and analysis with google SEO this only for large broiler integrators. | D23: 45780 | E23: Training Contract Broiler Farmers in Modern Practices to Maximize Yield and Minimize Losses | F23: https://www.poultry.care/blog/training-contract-broiler-farmers-in-modern-practices-to-maximize-yield-and-minimize-losses | G23: https://medium.com/@Sales_96467/training-contract-broiler-farmers-in-modern-practices-to-maximize-yield-and-minimize-losses-a59b27044ff3
A24: 23 | B24: Addressing Bird Shortages with Better Planning in Contract Broiler Farming | C24: =CONCATENATE("Act as a founder of PoultryCare ERP as Cloud-based ERP solution specific to poultry industry, which serves for all poultry segments like layer, broiler, breeder, broiler integration, hatchery, feedmill and processing plant. As you have experience in both "&"technology and hand-holding exposer with poultry farm owners, use your journey of this into opportunity to address poultry farmer's business needs, pain points and problems through blogs. You play the role of Content marketing head to position PoultryCare"&" ERP using organic content marketing. You Are planning to run a blog for Feed Mill management and educate a poultry farmers, to resolving their", B24," give heading for run a blog for educating poultry farmers with their tone to create more engagement Write a title with SEO keywords to hook visitors to continue reading, description for google SEO,Blogs convert traffic into leads. Blogs go above and beyo"&"nd product descriptions. blog content around 1000 words with more detailed explanation having 4 to 6 sub-headings and 4 tags. give the 3 keywords, Don't mention PoltryCare ERP anywhere Content should be Farmel understanding tone to create more engagement "&"and analysis with google SEO this only for large broiler integrators.") -> Act as a founder of PoultryCare ERP as Cloud-based ERP solution specific to poultry industry, which serves for all poultry segments like layer, broiler, breeder, broiler integration, hatchery, feedmill and processing plant. As you have experience in both technology and hand-holding exposer with poultry farm owners, use your journey of this into opportunity to address poultry farmer's business needs, pain points and problems through blogs. You play the role of Content marketing head to position PoultryCare ERP using organic content marketing. You Are planning to run a blog for Feed Mill management and educate a poultry farmers, to resolving theirAddressing Bird Shortages with Better Planning in Contract Broiler Farming give heading for run a blog for educating poultry farmers with their tone to create more engagement Write a title with SEO keywords to hook visitors to continue reading, description for google SEO,Blogs convert traffic into leads. Blogs go above and beyond product descriptions. blog content around 1000 words with more detailed explanation having 4 to 6 sub-headings and 4 tags. give the 3 keywords, Don't mention PoltryCare ERP anywhere Content should be Farmel understanding tone to create more engagement and analysis with google SEO this only for large broiler integrators. | D24: 45781 | E24: How Better Planning in Contract Broiler Farming Can Solve Bird Shortages at the Feed Mill | F24: https://www.poultry.care/blog/how-better-planning-in-contract-broiler-farming-can-solve-bird-shortages-at-the-feed-mill
A25: 24 | B25: Monitoring and Improving Farm Visits in Contract Broiler Farming | C25: =CONCATENATE("Act as a founder of PoultryCare ERP as Cloud-based ERP solution specific to poultry industry, which serves for all poultry segments like layer, broiler, breeder, broiler integration, hatchery, feedmill and processing plant. As you have experience in both "&"technology and hand-holding exposer with poultry farm owners, use your journey of this into opportunity to address poultry farmer's business needs, pain points and problems through blogs. You play the role of Content marketing head to position PoultryCare"&" ERP using organic content marketing. You Are planning to run a blog for Feed Mill management and educate a poultry farmers, to resolving their", B25," give heading for run a blog for educating poultry farmers with their tone to create more engagement Write a title with SEO keywords to hook visitors to continue reading, description for google SEO,Blogs convert traffic into leads. Blogs go above and beyo"&"nd product descriptions. blog content around 1000 words with more detailed explanation having 4 to 6 sub-headings and 4 tags. give the 3 keywords, Don't mention PoltryCare ERP anywhere Content should be Farmel understanding tone to create more engagement "&"and analysis with google SEO this only for large broiler integrators.") -> Act as a founder of PoultryCare ERP as Cloud-based ERP solution specific to poultry industry, which serves for all poultry segments like layer, broiler, breeder, broiler integration, hatchery, feedmill and processing plant. As you have experience in both technology and hand-holding exposer with poultry farm owners, use your journey of this into opportunity to address poultry farmer's business needs, pain points and problems through blogs. You play the role of Content marketing head to position PoultryCare ERP using organic content marketing. You Are planning to run a blog for Feed Mill management and educate a poultry farmers, to resolving theirMonitoring and Improving Farm Visits in Contract Broiler Farming give heading for run a blog for educating poultry farmers with their tone to create more engagement Write a title with SEO keywords to hook visitors to continue reading, description for google SEO,Blogs convert traffic into leads. Blogs go above and beyond product descriptions. blog content around 1000 words with more detailed explanation having 4 to 6 sub-headings and 4 tags. give the 3 keywords, Don't mention PoltryCare ERP anywhere Content should be Farmel understanding tone to create more engagement and analysis with google SEO this only for large broiler integrators. | D25: 45783 | E25: How to Monitor and Improve Farm Visits in Contract Broiler Farming for Better Performance | F25: https://www.poultry.care/blog/how-to-monitor-and-improve-farm-visits-in-contract-broiler-farming-for-better-performance
A26: 25 | B26: Managing Feed Conversion Ratio (FCR) for Higher Efficiency in Contract Broiler Farming | C26: =CONCATENATE("Act as a founder of PoultryCare ERP as Cloud-based ERP solution specific to poultry industry, which serves for all poultry segments like layer, broiler, breeder, broiler integration, hatchery, feedmill and processing plant. As you have experience in both "&"technology and hand-holding exposer with poultry farm owners, use your journey of this into opportunity to address poultry farmer's business needs, pain points and problems through blogs. You play the role of Content marketing head to position PoultryCare"&" ERP using organic content marketing. You Are planning to run a blog for Feed Mill management and educate a poultry farmers, to resolving their", B26," give heading for run a blog for educating poultry farmers with their tone to create more engagement Write a title with SEO keywords to hook visitors to continue reading, description for google SEO,Blogs convert traffic into leads. Blogs go above and beyo"&"nd product descriptions. blog content around 1000 words with more detailed explanation having 4 to 6 sub-headings and 4 tags. give the 3 keywords, Don't mention PoltryCare ERP anywhere Content should be Farmel understanding tone to create more engagement "&"and analysis with google SEO this only for large broiler integrators.") -> Act as a founder of PoultryCare ERP as Cloud-based ERP solution specific to poultry industry, which serves for all poultry segments like layer, broiler, breeder, broiler integration, hatchery, feedmill and processing plant. As you have experience in both technology and hand-holding exposer with poultry farm owners, use your journey of this into opportunity to address poultry farmer's business needs, pain points and problems through blogs. You play the role of Content marketing head to position PoultryCare ERP using organic content marketing. You Are planning to run a blog for Feed Mill management and educate a poultry farmers, to resolving theirManaging Feed Conversion Ratio (FCR) for Higher Efficiency in Contract Broiler Farming give heading for run a blog for educating poultry farmers with their tone to create more engagement Write a title with SEO keywords to hook visitors to continue reading, description for google SEO,Blogs convert traffic into leads. Blogs go above and beyond product descriptions. blog content around 1000 words with more detailed explanation having 4 to 6 sub-headings and 4 tags. give the 3 keywords, Don't mention PoltryCare ERP anywhere Content should be Farmel understanding tone to create more engagement and analysis with google SEO this only for large broiler integrators. | D26: 45784 | E26: Managing Feed Conversion Ratio in Contract Broiler Farming for Better Efficiency and Profit | F26: https://www.poultry.care/blog/managing-feed-conversion-ratio-in-contract-broiler-farming-for-better-efficiency-and-profit
A27: 26 | B27: Solving Low Body Weight Issues in Contract Broiler Farming | C27: =CONCATENATE("Act as a founder of PoultryCare ERP as Cloud-based ERP solution specific to poultry industry, which serves for all poultry segments like layer, broiler, breeder, broiler integration, hatchery, feedmill and processing plant. As you have experience in both "&"technology and hand-holding exposer with poultry farm owners, use your journey of this into opportunity to address poultry farmer's business needs, pain points and problems through blogs. You play the role of Content marketing head to position PoultryCare"&" ERP using organic content marketing. You Are planning to run a blog for Feed Mill management and educate a poultry farmers, to resolving their", B27," give heading for run a blog for educating poultry farmers with their tone to create more engagement Write a title with SEO keywords to hook visitors to continue reading, description for google SEO,Blogs convert traffic into leads. Blogs go above and beyo"&"nd product descriptions. blog content around 1000 words with more detailed explanation having 4 to 6 sub-headings and 4 tags. give the 3 keywords, Don't mention PoltryCare ERP anywhere Content should be Farmel understanding tone to create more engagement "&"and analysis with google SEO this only for large broiler integrators.") -> Act as a founder of PoultryCare ERP as Cloud-based ERP solution specific to poultry industry, which serves for all poultry segments like layer, broiler, breeder, broiler integration, hatchery, feedmill and processing plant. As you have experience in both technology and hand-holding exposer with poultry farm owners, use your journey of this into opportunity to address poultry farmer's business needs, pain points and problems through blogs. You play the role of Content marketing head to position PoultryCare ERP using organic content marketing. You Are planning to run a blog for Feed Mill management and educate a poultry farmers, to resolving theirSolving Low Body Weight Issues in Contract Broiler Farming give heading for run a blog for educating poultry farmers with their tone to create more engagement Write a title with SEO keywords to hook visitors to continue reading, description for google SEO,Blogs convert traffic into leads. Blogs go above and beyond product descriptions. blog content around 1000 words with more detailed explanation having 4 to 6 sub-headings and 4 tags. give the 3 keywords, Don't mention PoltryCare ERP anywhere Content should be Farmel understanding tone to create more engagement and analysis with google SEO this only for large broiler integrators. | D27: 45785 | E27: How to Solve Low Body Weight Issues in Contract Broiler Farming and Maximize FCR Efficiency | F27: https://www.poultry.care/blog/how-to-solve-low-body-weight-issues-in-contract-broiler-farming-and-maximize-fcr-efficiency
A28: 27 | B28: Best Practices for Biosecurity to Protect Your Contract Broiler Farm | C28: =CONCATENATE("Act as a founder of PoultryCare ERP as Cloud-based ERP solution specific to poultry industry, which serves for all poultry segments like layer, broiler, breeder, broiler integration, hatchery, feedmill and processing plant. As you have experience in both "&"technology and hand-holding exposer with poultry farm owners, use your journey of this into opportunity to address poultry farmer's business needs, pain points and problems through blogs. You play the role of Content marketing head to position PoultryCare"&" ERP using organic content marketing. You Are planning to run a blog for Feed Mill management and educate a poultry farmers, to resolving their", B28," give heading for run a blog for educating poultry farmers with their tone to create more engagement Write a title with SEO keywords to hook visitors to continue reading, description for google SEO,Blogs convert traffic into leads. Blogs go above and beyo"&"nd product descriptions. blog content around 1000 words with more detailed explanation having 4 to 6 sub-headings and 4 tags. give the 3 keywords, Don't mention PoltryCare ERP anywhere Content should be Farmel understanding tone to create more engagement "&"and analysis with google SEO this only for large broiler integrators.") -> Act as a founder of PoultryCare ERP as Cloud-based ERP solution specific to poultry industry, which serves for all poultry segments like layer, broiler, breeder, broiler integration, hatchery, feedmill and processing plant. As you have experience in both technology and hand-holding exposer with poultry farm owners, use your journey of this into opportunity to address poultry farmer's business needs, pain points and problems through blogs. You play the role of Content marketing head to position PoultryCare ERP using organic content marketing. You Are planning to run a blog for Feed Mill management and educate a poultry farmers, to resolving theirBest Practices for Biosecurity to Protect Your Contract Broiler Farm give heading for run a blog for educating poultry farmers with their tone to create more engagement Write a title with SEO keywords to hook visitors to continue reading, description for google SEO,Blogs convert traffic into leads. Blogs go above and beyond product descriptions. blog content around 1000 words with more detailed explanation having 4 to 6 sub-headings and 4 tags. give the 3 keywords, Don't mention PoltryCare ERP anywhere Content should be Farmel understanding tone to create more engagement and analysis with google SEO this only for large broiler integrators. | D28: 45786 | E28: Best Practices for Biosecurity in Contract Broiler Farming to Prevent Disease and Improve Flock Health | F28: https://www.poultry.care/blog/best-practices-for-biosecurity-in-contract-broiler-farming-to-prevent-disease-and-improve-flock-health
A29: 28 | B29: Identifying and Controlling High Feed Intake in Contract Broiler Farming | C29: =CONCATENATE("Act as a founder of PoultryCare ERP as Cloud-based ERP solution specific to poultry industry, which serves for all poultry segments like layer, broiler, breeder, broiler integration, hatchery, feedmill and processing plant. As you have experience in both "&"technology and hand-holding exposer with poultry farm owners, use your journey of this into opportunity to address poultry farmer's business needs, pain points and problems through blogs. You play the role of Content marketing head to position PoultryCare"&" ERP using organic content marketing. You Are planning to run a blog for Feed Mill management and educate a poultry farmers, to resolving their", B29," give heading for run a blog for educating poultry farmers with their tone to create more engagement Write a title with SEO keywords to hook visitors to continue reading, description for google SEO,Blogs convert traffic into leads. Blogs go above and beyo"&"nd product descriptions. blog content around 1000 words with more detailed explanation having 4 to 6 sub-headings and 4 tags. give the 3 keywords, Don't mention PoltryCare ERP anywhere Content should be Farmel understanding tone to create more engagement "&"and analysis with google SEO this only for large broiler integrators.") -> Act as a founder of PoultryCare ERP as Cloud-based ERP solution specific to poultry industry, which serves for all poultry segments like layer, broiler, breeder, broiler integration, hatchery, feedmill and processing plant. As you have experience in both technology and hand-holding exposer with poultry farm owners, use your journey of this into opportunity to address poultry farmer's business needs, pain points and problems through blogs. You play the role of Content marketing head to position PoultryCare ERP using organic content marketing. You Are planning to run a blog for Feed Mill management and educate a poultry farmers, to resolving theirIdentifying and Controlling High Feed Intake in Contract Broiler Farming give heading for run a blog for educating poultry farmers with their tone to create more engagement Write a title with SEO keywords to hook visitors to continue reading, description for google SEO,Blogs convert traffic into leads. Blogs go above and beyond product descriptions. blog content around 1000 words with more detailed explanation having 4 to 6 sub-headings and 4 tags. give the 3 keywords, Don't mention PoltryCare ERP anywhere Content should be Farmel understanding tone to create more engagement and analysis with google SEO this only for large broiler integrators. | D29: 45787 | E29: How to Identify and Control High Feed Intake in Contract Broiler Farming for Better Efficiency | F29: https://www.poultry.care/blog/how-to-identify-and-control-high-feed-intake-in-contract-broiler-farming-for-better-efficiency
A30: 29 | B30: Handling High Bird Placement Rates Without Overburdening Your Contract Broiler Farm | C30: =CONCATENATE("Act as a founder of PoultryCare ERP as Cloud-based ERP solution specific to poultry industry, which serves for all poultry segments like layer, broiler, breeder, broiler integration, hatchery, feedmill and processing plant. As you have experience in both "&"technology and hand-holding exposer with poultry farm owners, use your journey of this into opportunity to address poultry farmer's business needs, pain points and problems through blogs. You play the role of Content marketing head to position PoultryCare"&" ERP using organic content marketing. You Are planning to run a blog for Feed Mill management and educate a poultry farmers, to resolving their", B30," give heading for run a blog for educating poultry farmers with their tone to create more engagement Write a title with SEO keywords to hook visitors to continue reading, description for google SEO,Blogs convert traffic into leads. Blogs go above and beyo"&"nd product descriptions. blog content around 1000 words with more detailed explanation having 4 to 6 sub-headings and 4 tags. give the 3 keywords, Don't mention PoltryCare ERP anywhere Content should be Farmel understanding tone to create more engagement "&"and analysis with google SEO this only for large broiler integrators.") -> Act as a founder of PoultryCare ERP as Cloud-based ERP solution specific to poultry industry, which serves for all poultry segments like layer, broiler, breeder, broiler integration, hatchery, feedmill and processing plant. As you have experience in both technology and hand-holding exposer with poultry farm owners, use your journey of this into opportunity to address poultry farmer's business needs, pain points and problems through blogs. You play the role of Content marketing head to position PoultryCare ERP using organic content marketing. You Are planning to run a blog for Feed Mill management and educate a poultry farmers, to resolving theirHandling High Bird Placement Rates Without Overburdening Your Contract Broiler Farm give heading for run a blog for educating poultry farmers with their tone to create more engagement Write a title with SEO keywords to hook visitors to continue reading, description for google SEO,Blogs convert traffic into leads. Blogs go above and beyond product descriptions. blog content around 1000 words with more detailed explanation having 4 to 6 sub-headings and 4 tags. give the 3 keywords, Don't mention PoltryCare ERP anywhere Content should be Farmel understanding tone to create more engagement and analysis with google SEO this only for large broiler integrators. | D30: 45788 | E30: How to Manage High Bird Placement Rates in Contract Broiler Farming Without Overloading Your Farms | F30: https://www.poultry.care/blog/how-to-manage-high-bird-placement-rates-in-contract-broiler-farming-without-overloading-your-farms
A31: 30 | B31: Managing Employee Challenges on Your Contract Broiler Farm | C31: =CONCATENATE("Act as a founder of PoultryCare ERP as Cloud-based ERP solution specific to poultry industry, which serves for all poultry segments like layer, broiler, breeder, broiler integration, hatchery, feedmill and processing plant. As you have experience in both "&"technology and hand-holding exposer with poultry farm owners, use your journey of this into opportunity to address poultry farmer's business needs, pain points and problems through blogs. You play the role of Content marketing head to position PoultryCare"&" ERP using organic content marketing. You Are planning to run a blog for Feed Mill management and educate a poultry farmers, to resolving their", B31," give heading for run a blog for educating poultry farmers with their tone to create more engagement Write a title with SEO keywords to hook visitors to continue reading, description for google SEO,Blogs convert traffic into leads. Blogs go above and beyo"&"nd product descriptions. blog content around 1000 words with more detailed explanation having 4 to 6 sub-headings and 4 tags. give the 3 keywords, Don't mention PoltryCare ERP anywhere Content should be Farmel understanding tone to create more engagement "&"and analysis with google SEO this only for large broiler integrators.") -> Act as a founder of PoultryCare ERP as Cloud-based ERP solution specific to poultry industry, which serves for all poultry segments like layer, broiler, breeder, broiler integration, hatchery, feedmill and processing plant. As you have experience in both technology and hand-holding exposer with poultry farm owners, use your journey of this into opportunity to address poultry farmer's business needs, pain points and problems through blogs. You play the role of Content marketing head to position PoultryCare ERP using organic content marketing. You Are planning to run a blog for Feed Mill management and educate a poultry farmers, to resolving theirManaging Employee Challenges on Your Contract Broiler Farm give heading for run a blog for educating poultry farmers with their tone to create more engagement Write a title with SEO keywords to hook visitors to continue reading, description for google SEO,Blogs convert traffic into leads. Blogs go above and beyond product descriptions. blog content around 1000 words with more detailed explanation having 4 to 6 sub-headings and 4 tags. give the 3 keywords, Don't mention PoltryCare ERP anywhere Content should be Farmel understanding tone to create more engagement and analysis with google SEO this only for large broiler integrators. | D31: 45789 | E31: Managing Farm Staff Challenges in Contract Broiler Farming for Better Productivity | F31: https://www.poultry.care/blog/managing-farm-staff-challenges-in-contract-broiler-farming-for-better-productivity
A32: 31 | B32: Inter-Farm Feed Transfers in Contract Broiler Farming: How to Manage and Monitor | C32: =CONCATENATE("Act as a founder of PoultryCare ERP as Cloud-based ERP solution specific to poultry industry, which serves for all poultry segments like layer, broiler, breeder, broiler integration, hatchery, feedmill and processing plant. As you have experience in both "&"technology and hand-holding exposer with poultry farm owners, use your journey of this into opportunity to address poultry farmer's business needs, pain points and problems through blogs. You play the role of Content marketing head to position PoultryCare"&" ERP using organic content marketing. You Are planning to run a blog for Feed Mill management and educate a poultry farmers, to resolving their", B32," give heading for run a blog for educating poultry farmers with their tone to create more engagement Write a title with SEO keywords to hook visitors to continue reading, description for google SEO,Blogs convert traffic into leads. Blogs go above and beyo"&"nd product descriptions. blog content around 1000 words with more detailed explanation having 4 to 6 sub-headings and 4 tags. give the 3 keywords, Don't mention PoltryCare ERP anywhere Content should be Farmel understanding tone to create more engagement "&"and analysis with google SEO this only for large broiler integrators.") -> Act as a founder of PoultryCare ERP as Cloud-based ERP solution specific to poultry industry, which serves for all poultry segments like layer, broiler, breeder, broiler integration, hatchery, feedmill and processing plant. As you have experience in both technology and hand-holding exposer with poultry farm owners, use your journey of this into opportunity to address poultry farmer's business needs, pain points and problems through blogs. You play the role of Content marketing head to position PoultryCare ERP using organic content marketing. You Are planning to run a blog for Feed Mill management and educate a poultry farmers, to resolving theirInter-Farm Feed Transfers in Contract Broiler Farming: How to Manage and Monitor give heading for run a blog for educating poultry farmers with their tone to create more engagement Write a title with SEO keywords to hook visitors to continue reading, description for google SEO,Blogs convert traffic into leads. Blogs go above and beyond product descriptions. blog content around 1000 words with more detailed explanation having 4 to 6 sub-headings and 4 tags. give the 3 keywords, Don't mention PoltryCare ERP anywhere Content should be Farmel understanding tone to create more engagement and analysis with google SEO this only for large broiler integrators. | D32: 45790 | E32: Inter Farm Feed Transfers in Contract Broiler Farming Managing Shortages with Better Control | F32: https://www.poultry.care/blog/inter-farm-feed-transfers-in-contract-broiler-farming-managing-shortages-with-better-control
A33: 32 | B33: Understanding Climate Change and Its Impact on Contract Broiler Farming | C33: =CONCATENATE("Act as a founder of PoultryCare ERP as Cloud-based ERP solution specific to poultry industry, which serves for all poultry segments like layer, broiler, breeder, broiler integration, hatchery, feedmill and processing plant. As you have experience in both "&"technology and hand-holding exposer with poultry farm owners, use your journey of this into opportunity to address poultry farmer's business needs, pain points and problems through blogs. You play the role of Content marketing head to position PoultryCare"&" ERP using organic content marketing. You Are planning to run a blog for Feed Mill management and educate a poultry farmers, to resolving their", B33," give heading for run a blog for educating poultry farmers with their tone to create more engagement Write a title with SEO keywords to hook visitors to continue reading, description for google SEO,Blogs convert traffic into leads. Blogs go above and beyo"&"nd product descriptions. blog content around 1000 words with more detailed explanation having 4 to 6 sub-headings and 4 tags. give the 3 keywords, Don't mention PoltryCare ERP anywhere Content should be Farmel understanding tone to create more engagement "&"and analysis with google SEO this only for large broiler integrators.") -> Act as a founder of PoultryCare ERP as Cloud-based ERP solution specific to poultry industry, which serves for all poultry segments like layer, broiler, breeder, broiler integration, hatchery, feedmill and processing plant. As you have experience in both technology and hand-holding exposer with poultry farm owners, use your journey of this into opportunity to address poultry farmer's business needs, pain points and problems through blogs. You play the role of Content marketing head to position PoultryCare ERP using organic content marketing. You Are planning to run a blog for Feed Mill management and educate a poultry farmers, to resolving theirUnderstanding Climate Change and Its Impact on Contract Broiler Farming give heading for run a blog for educating poultry farmers with their tone to create more engagement Write a title with SEO keywords to hook visitors to continue reading, description for google SEO,Blogs convert traffic into leads. Blogs go above and beyond product descriptions. blog content around 1000 words with more detailed explanation having 4 to 6 sub-headings and 4 tags. give the 3 keywords, Don't mention PoltryCare ERP anywhere Content should be Farmel understanding tone to create more engagement and analysis with google SEO this only for large broiler integrators. | D33: 45791 | E33: Understanding Climate Change Impact on Contract Broiler Farming for Better Preparedness | F33: https://www.poultry.care/blog/understanding-climate-change-impact-on-contract-broiler-farming-for-better-preparedness
A34: 33 | B34: Developing Feed Standards for Consistent Performance in Contract Broiler Farming | C34: =CONCATENATE("Act as a founder of PoultryCare ERP as Cloud-based ERP solution specific to poultry industry, which serves for all poultry segments like layer, broiler, breeder, broiler integration, hatchery, feedmill and processing plant. As you have experience in both "&"technology and hand-holding exposer with poultry farm owners, use your journey of this into opportunity to address poultry farmer's business needs, pain points and problems through blogs. You play the role of Content marketing head to position PoultryCare"&" ERP using organic content marketing. You Are planning to run a blog for Feed Mill management and educate a poultry farmers, to resolving their", B34," give heading for run a blog for educating poultry farmers with their tone to create more engagement Write a title with SEO keywords to hook visitors to continue reading, description for google SEO,Blogs convert traffic into leads. Blogs go above and beyo"&"nd product descriptions. blog content around 1000 words with more detailed explanation having 4 to 6 sub-headings and 4 tags. give the 3 keywords, Don't mention PoltryCare ERP anywhere Content should be Farmel understanding tone to create more engagement "&"and analysis with google SEO this only for large broiler integrators.") -> Act as a founder of PoultryCare ERP as Cloud-based ERP solution specific to poultry industry, which serves for all poultry segments like layer, broiler, breeder, broiler integration, hatchery, feedmill and processing plant. As you have experience in both technology and hand-holding exposer with poultry farm owners, use your journey of this into opportunity to address poultry farmer's business needs, pain points and problems through blogs. You play the role of Content marketing head to position PoultryCare ERP using organic content marketing. You Are planning to run a blog for Feed Mill management and educate a poultry farmers, to resolving theirDeveloping Feed Standards for Consistent Performance in Contract Broiler Farming give heading for run a blog for educating poultry farmers with their tone to create more engagement Write a title with SEO keywords to hook visitors to continue reading, description for google SEO,Blogs convert traffic into leads. Blogs go above and beyond product descriptions. blog content around 1000 words with more detailed explanation having 4 to 6 sub-headings and 4 tags. give the 3 keywords, Don't mention PoltryCare ERP anywhere Content should be Farmel understanding tone to create more engagement and analysis with google SEO this only for large broiler integrators. | D34: 45792 | E34: Developing Feed Standards in Contract Broiler Farming for Consistent Bird Performance | F34: https://www.poultry.care/blog/developing-feed-standards-in-contract-broiler-farming-for-consistent-bird-performance
A35: 34 | B35: Accurately Measuring and Recording Bodyweight in Contract Broiler Farming | C35: =CONCATENATE("Act as a founder of PoultryCare ERP as Cloud-based ERP solution specific to poultry industry, which serves for all poultry segments like layer, broiler, breeder, broiler integration, hatchery, feedmill and processing plant. As you have experience in both "&"technology and hand-holding exposer with poultry farm owners, use your journey of this into opportunity to address poultry farmer's business needs, pain points and problems through blogs. You play the role of Content marketing head to position PoultryCare"&" ERP using organic content marketing. You Are planning to run a blog for Feed Mill management and educate a poultry farmers, to resolving their", B35," give heading for run a blog for educating poultry farmers with their tone to create more engagement Write a title with SEO keywords to hook visitors to continue reading, description for google SEO,Blogs convert traffic into leads. Blogs go above and beyo"&"nd product descriptions. blog content around 1000 words with more detailed explanation having 4 to 6 sub-headings and 4 tags. give the 3 keywords, Don't mention PoltryCare ERP anywhere Content should be Farmel understanding tone to create more engagement "&"and analysis with google SEO this only for large broiler integrators.") -> Act as a founder of PoultryCare ERP as Cloud-based ERP solution specific to poultry industry, which serves for all poultry segments like layer, broiler, breeder, broiler integration, hatchery, feedmill and processing plant. As you have experience in both technology and hand-holding exposer with poultry farm owners, use your journey of this into opportunity to address poultry farmer's business needs, pain points and problems through blogs. You play the role of Content marketing head to position PoultryCare ERP using organic content marketing. You Are planning to run a blog for Feed Mill management and educate a poultry farmers, to resolving theirAccurately Measuring and Recording Bodyweight in Contract Broiler Farming give heading for run a blog for educating poultry farmers with their tone to create more engagement Write a title with SEO keywords to hook visitors to continue reading, description for google SEO,Blogs convert traffic into leads. Blogs go above and beyond product descriptions. blog content around 1000 words with more detailed explanation having 4 to 6 sub-headings and 4 tags. give the 3 keywords, Don't mention PoltryCare ERP anywhere Content should be Farmel understanding tone to create more engagement and analysis with google SEO this only for large broiler integrators. | D35: 45793 | E35: How to Accurately Measure and Record Bodyweight in Contract Broiler Farming for Better Flock Performance | F35: https://www.poultry.care/blog/how-to-accurately-measure-and-record-bodyweight-in-contract-broiler-farming-for-better-flock-performance
... A51: 50 | B51: Using Breed Standards to Ensure Optimal Performance in Contract Broiler Farming | C51: =CONCATENATE("Act as a founder of PoultryCare ERP as Cloud-based ERP solution specific to poultry industry, which serves for all poultry segments like layer, broiler, breeder, broiler integration, hatchery, feedmill and processing plant. As you have experience in both "&"technology and hand-holding exposer with poultry farm owners, use your journey of this into opportunity to address poultry farmer's business needs, pain points and problems through blogs. You play the role of Content marketing head to position PoultryCare"&" ERP using organic content marketing. You Are planning to run a blog for Feed Mill management and educate a poultry farmers, to resolving their", B51," give heading for run a blog for educating poultry farmers with their tone to create more engagement Write a title with SEO keywords to hook visitors to continue reading, description for google SEO,Blogs convert traffic into leads. Blogs go above and beyo"&"nd product descriptions. blog content around 1000 words with more detailed explanation having 4 to 6 sub-headings and 4 tags. give the 3 keywords, Don't mention PoltryCare ERP anywhere Content should be Farmel understanding tone to create more engagement "&"and analysis with google SEO this only for large broiler integrators.") -> Act as a founder of PoultryCare ERP as Cloud-based ERP solution specific to poultry industry, which serves for all poultry segments like layer, broiler, breeder, broiler integration, hatchery, feedmill and processing plant. As you have experience in both technology and hand-holding exposer with poultry farm owners, use your journey of this into opportunity to address poultry farmer's business needs, pain points and problems through blogs. You play the role of Content marketing head to position PoultryCare ERP using organic content marketing. You Are planning to run a blog for Feed Mill management and educate a poultry farmers, to resolving theirUsing Breed Standards to Ensure Optimal Performance in Contract Broiler Farming give heading for run a blog for educating poultry farmers with their tone to create more engagement Write a title with SEO keywords to hook visitors to continue reading, description for google SEO,Blogs convert traffic into leads. Blogs go above and beyond product descriptions. blog content around 1000 words with more detailed explanation having 4 to 6 sub-headings and 4 tags. give the 3 keywords, Don't mention PoltryCare ERP anywhere Content should be Farmel understanding tone to create more engagement and analysis with google SEO this only for large broiler integrators. | D51: 45809 | E51: Using Breed Standards to Drive Consistency and Performance in Contract Broiler Farming | F51: https://www.poultry.care/blog/using-breed-standards-to-drive-consistency-and-performance-in-contract-broiler-farming

Sheet Format
C1: Date | K1: Role | L1: information | M1: Essential | N1: Top | O1: Method | P1: Guidelines | Q1: Benefits
A2: How to Reduce High Mortality in Contract Broiler Farming | B2: Tip: Maintain good biosecurity and a clean environment to lower bird mortality.
A3: Improving Feed Supply Chain for Consistent Growth | B3: Tip: Plan feed orders in advance to avoid shortages and ensure birds get the right nutrition.
A4: Investment Planning for Contract Broiler Farming: Smart Strategies | B4: Tip: Set a clear budget for each farming cycle to avoid unexpected costs.
A5: Managing Bird Deliveries Efficiently for Smooth Operations | B5: Tip: Schedule bird deliveries early to ensure proper preparation and reduce stress on chicks.
A6: Handling Climate Change in Contract Broiler Farming | B6: Tip: Install temperature control systems to protect birds during extreme weather.
A7: Keeping Data Safe: Best Practices for Farm Records | B7: Tip: Store farm data securely and back it up regularly to prevent loss or manipulation.
A8: Cutting Down Feed Purchase Costs Without Sacrificing Quality | B8: Tip: Bulk-buy feed at the best rates and store it properly to reduce wastage.
A9: Maximizing the Impact of Farm Supervisors' Visits | B9: Tip: Regular supervisor visits help catch small issues early before they become big problems.
A10: How to Prevent Feed Overstocking in Contract Broiler Farming | B10: Tip: Track daily feed usage to avoid over-purchasing and spoilage.
A11: Managing Multiple Chick Placements with Less Hassle | B11: Tip: Space out chick placements to give enough time for proper brooding.
A12: Following the Recommended Feed Formula for Better Growth | B12: Tip: Use the right feed formula for each growth stage to ensure healthy birds.
A13: Mastering Brooding Techniques for Strong, Healthy Chicks | B13: Tip: Keep the brooding area warm and clean to give chicks a good start.
... A61: Managing Supplier and Customer Due Amounts to Improve Cash Flow | B61: Tip: Keep track of due payments to suppliers and customers to maintain healthy cash flow.

Sheet Content
A1: Farm | B1: Categories | C1: NDP | D1: Keywords | E1: Raw Title | F1: Target page | G1: Target Keyword | H1: Content | I1: Date | J1: Final Title | K1: Tone | L1: prompt | M1: Blog URL | N1: Prompt for LinkedIn | O1: Prompt for Facebook | P1: Prompt for Instagram | Q1: prompt for twitter | R1: prompt for Reel | S1: Date | T1: Quick tip
A2: Contract Broiler Farming/Broiler Integration | B2: Fear | C2: High Mortality | D2: weather prepareness | E2: Be Prepared: Weather Preparedness in Contract Broiler Farming | G2: reduce mortality | H2: supervisior should train farmer on weather condition and how to be prepared on that condition | I2: 45246 | J2: A COMPREHENSIVE GUIDE TO WEATHER PREPAREDNESS IN CONTRACT BROILER FARMING | K2: Empathetic | L2: =CONCATENATE(Instructions!$B$1, " ", Instructions!$B$2, " ", A2, " farmers ", B2, " about ", C2, ". Based on my experiance I suggest ", H2 ," for better guidance. Write a blog to highlight ", D2, " to match ", E2, " which generates traffic for landing page matching title ", F2, ". ",Instructions!$B$4, " Content should be " ,K2, " tone to create more engagement.") -> Consider yourself founder of PoultryCare ERP as Cloud-based ERP solution specific to poultry industry, which serves for all poultry segments like layer, broiler, breeder, broiler integration, hatchery, feedmill and processing plant. As you have experience in both technology and hand-holding exposer with poultry farm owners, use your journey of this into opportunity to address poultry farmer's business needs, pain points and problems through blogs. You play the role of Content marketing head to position PoultryCare ERP using organic content marketing. Contract Broiler Farming/Broiler Integration farmers Fear about High Mortality. Based on my experiance I suggest supervisior should train farmer on weather condition and how to be prepared on that condition for better guidance. Write a blog to highlight weather prepareness to match Be Prepared: Weather Preparedness in Contract Broiler Farming which generates traffic for landing page matching title . , description for google SEO, blog content around 5000 words with more detailed explanation having 4 to 6 sub-headings and 4 tags. Don't mention PoltryCare ERP anywhere Content should be Empathetic tone to create more engagement. | M2: https://www.poultry.care/blog/a-comprehensive-guide-to-weather-preparedness-in-contract-broiler-farming | N2: =CONCATENATE(Instructions!$B$1, " ", Instructions!$B$2, " ", A2, " farmers ", B2, " about ", C2, ". Based on my experiance I suggest ", H2 ," for better guidance. Write a LinkedIn post to highlight ", D2, " to match ", E2, " which generates more engagement and credibility for title ", F2, ". ",Instructions!$B$5, " Create link to url: ",M2 , " Content should be " ,K2, " tone to create more engagement.") -> Consider yourself founder of PoultryCare ERP as Cloud-based ERP solution specific to poultry industry, which serves for all poultry segments like layer, broiler, breeder, broiler integration, hatchery, feedmill and processing plant. As you have experience in both technology and hand-holding exposer with poultry farm owners, use your journey of this into opportunity to address poultry farmer's business needs, pain points and problems through blogs. You play the role of Content marketing head to position PoultryCare ERP using organic content marketing. Contract Broiler Farming/Broiler Integration farmers Fear about High Mortality. Based on my experiance I suggest supervisior should train farmer on weather condition and how to be prepared on that condition for better guidance. Write a LinkedIn post to highlight weather prepareness to match Be Prepared: Weather Preparedness in Contract Broiler Farming which generates more engagement and credibility for title . LinkedIn post as conversational format as Hook/question, insightful problem statement, solution for the problem, call-to-action for engagement. Dont include section titles in the content. All within maximum 300 words. Mention PoltryCare if possible in the content, also suggest 4 hashtags addition to #poultrycare each hash tag in small character Create link to url: https://www.poultry.care/blog/a-comprehensive-guide-to-weather-preparedness-in-contract-broiler-farming Content should be Empathetic tone to create more engagement. | O2: =CONCATENATE(Instructions!$B$1, " ", Instructions!$B$2, " ", A2, " farmers ", B2, " about ", C2, ". Based on my experiance I suggest ", H2 ," for better guidance. Write a Facebook post to highlight ", D2, " to match ", E2, " which generates more engagement and credibility for title ", F2, ". ",Instructions!$B$7, " Create link to url: ",M2 , " Content should be " ,K2, " tone to create more engagement.") -> Consider yourself founder of PoultryCare ERP as Cloud-based ERP solution specific to poultry industry, which serves for all poultry segments like layer, broiler, breeder, broiler integration, hatchery, feedmill and processing plant. As you have experience in both technology and hand-holding exposer with poultry farm owners, use your journey of this into opportunity to address poultry farmer's business needs, pain points and problems through blogs. You play the role of Content marketing head to position PoultryCare ERP using organic content marketing. Contract Broiler Farming/Broiler Integration farmers Fear about High Mortality. Based on my experiance I suggest supervisior should train farmer on weather condition and how to be prepared on that condition for better guidance. Write a Facebook post to highlight weather prepareness to match Be Prepared: Weather Preparedness in Contract Broiler Farming which generates more engagement and credibility for title . Facebook post as conversational format as Hook/question, insightful problem statement, solution for the problem, call-to-action for engagement. Dont include section titles in the content. All within maximum 300 words. Mention PoltryCare if possible in the content, also suggest 4 hashtags addition to #poultrycare each hash tag in small character Create link to url: https://www.poultry.care/blog/a-comprehensive-guide-to-weather-preparedness-in-contract-broiler-farming Content should be Empathetic tone to create more engagement. | P2: =CONCATENATE(Instructions!$B$1, " ", Instructions!$B$2, " ", A2, " farmers ", B2, " about ", C2, ". Based on my experiance I suggest ", H2 ," for better guidance. Write a Instagram post to highlight ", D2, " to match ", E2, " which generates more engagement and credibility for title ", F2, ". ",Instructions!$B$6, " Create link to url: ",M2 , " Content should be " ,K2, " tone to create more engagement.") -> Consider yourself founder of PoultryCare ERP as Cloud-based ERP solution specific to poultry industry, which serves for all poultry segments like layer, broiler, breeder, broiler integration, hatchery, feedmill and processing plant. As you have experience in both technology and hand-holding exposer with poultry farm owners, use your journey of this into opportunity to address poultry farmer's business needs, pain points and problems through blogs. You play the role of Content marketing head to position PoultryCare ERP using organic content marketing. Contract Broiler Farming/Broiler Integration farmers Fear about High Mortality. Based on my experiance I suggest supervisior should train farmer on weather condition and how to be prepared on that condition for better guidance. Write a Instagram post to highlight weather prepareness to match Be Prepared: Weather Preparedness in Contract Broiler Farming which generates more engagement and credibility for title . Instagram post as conversational format as Hook/question, insightful problem statement, solution for the problem, call-to-action for engagement. Dont include section titles in the content. All within maximum 300 words. Mention PoltryCare if possible in the content, also suggest 4 hashtags addition to #poultrycare each hash tag in small character Create link to url: https://www.poultry.care/blog/a-comprehensive-guide-to-weather-preparedness-in-contract-broiler-farming Content should be Empathetic tone to create more engagement. | Q2: =CONCATENATE(Instructions!$B$1, " ", Instructions!$B$2, " ", A2, " farmers ", B2, " about ", C2, ". Based on my experiance I suggest ", H2 ," for better guidance. Write a twitter post to highlight ", D2, " to match ", E2, " which generates more engagement and credibility for title ", F2, ". ",Instructions!$B$8, " Create link to url: ",M2 , " Content should be " ,K2, " tone to create more engagement.") -> Consider yourself founder of PoultryCare ERP as Cloud-based ERP solution specific to poultry industry, which serves for all poultry segments like layer, broiler, breeder, broiler integration, hatchery, feedmill and processing plant. As you have experience in both technology and hand-holding exposer with poultry farm owners, use your journey of this into opportunity to address poultry farmer's business needs, pain points and problems through blogs. You play the role of Content marketing head to position PoultryCare ERP using organic content marketing. Contract Broiler Farming/Broiler Integration farmers Fear about High Mortality. Based on my experiance I suggest supervisior should train farmer on weather condition and how to be prepared on that condition for better guidance. Write a twitter post to highlight weather prepareness to match Be Prepared: Weather Preparedness in Contract Broiler Farming which generates more engagement and credibility for title . Twitter post as conversational format as Hook/question, insightful problem statement, solution for the problem, call-to-action for engagement. Dont include section titles in the content. All within maximum 100 words. Mention PoltryCare if possible in the content, also suggest 4 hashtags addition to #poultrycare each hash tag in small character Create link to url: https://www.poultry.care/blog/a-comprehensive-guide-to-weather-preparedness-in-contract-broiler-farming Content should be Empathetic tone to create more engagement. | R2: =CONCATENATE("Consider yourself founder of PoultryCare ERP as Cloud-based ERP solution specific to poultry industry, which serves for all poultry segments like layer, broiler, breeder, broiler integration, hatchery, feedmill and processing plant. As you have experience"&" in both technology and hand-holding exposer with poultry farm owners, use your journey of this into opportunity to address poultry farmer's business needs, pain points and problems through blogs. You play the role of Content marketing head to position Po"&"ultryCare ERP using organic content marketing. Contract Broiler Farming/Broiler Integration Farmers ",B2," about ",C2,". Based on my experience I suggest ",H2,". Create script for www.narakeet.com to develop reals and shots video to highlight ",D2," to match ",E2," which generates traffic for landing page matching title. Template for video script for 30 sec, should be start with hook, highlight problem statement, give solution as pointer, end with punch. Add call to action to request PoultryCare subscription for si"&"milar tips and guides Content should be a friendly tone to create more subscribers") -> Consider yourself founder of PoultryCare ERP as Cloud-based ERP solution specific to poultry industry, which serves for all poultry segments like layer, broiler, breeder, broiler integration, hatchery, feedmill and processing plant. As you have experience in both technology and hand-holding exposer with poultry farm owners, use your journey of this into opportunity to address poultry farmer's business needs, pain points and problems through blogs. You play the role of Content marketing head to position PoultryCare ERP using organic content marketing. Contract Broiler Farming/Broiler Integration Farmers Fear about High Mortality. Based on my experience I suggest supervisior should train farmer on weather condition and how to be prepared on that condition. Create script for www.narakeet.com to develop reals and shots video to highlight weather prepareness to match Be Prepared: Weather Preparedness in Contract Broiler Farming which generates traffic for landing page matching title. Template for video script for 30 sec, should be start with hook, highlight problem statement, give solution as pointer, end with punch. Add call to action to request PoultryCare subscription for similar tips and guides Content should be a friendly tone to create more subscribers | S2: 45279
A3: Contract Broiler Farming/Broiler Integration | B3: Fear | C3: High Mortality | D3: Contract Broiler Farming Disease Management | E3: Contract Broiler Farming Disease symptoms and treatments | G3: reduce mortality, avoid diseases | H3: supervisior should train farmer on Disease and how to be prepared on that sutivation | I3: 45247 | J3: STEP-BY-STEP GUIDE TO MANAGING DISEASES IN CONTRACT BROILER FARMING FOR REDUCED MORTALITY | L3: =CONCATENATE(Instructions!$B$1, " ", Instructions!$B$2, " ", A3, " farmers ", B3, " about ", C3, ". Based on my experiance I suggest ", H3 ," for better guidance. Write a blog to highlight ", D3, " to match ", E3, " which generates traffic for landing page matching title ", F3, ". ",Instructions!$B$4, " Content should be " ,K3, " tone to create more engagement.") -> Consider yourself founder of PoultryCare ERP as Cloud-based ERP solution specific to poultry industry, which serves for all poultry segments like layer, broiler, breeder, broiler integration, hatchery, feedmill and processing plant. As you have experience in both technology and hand-holding exposer with poultry farm owners, use your journey of this into opportunity to address poultry farmer's business needs, pain points and problems through blogs. You play the role of Content marketing head to position PoultryCare ERP using organic content marketing. Contract Broiler Farming/Broiler Integration farmers Fear about High Mortality. Based on my experiance I suggest supervisior should train farmer on Disease and how to be prepared on that sutivation for better guidance. Write a blog to highlight Contract Broiler Farming Disease Management to match Contract Broiler Farming Disease symptoms and treatments which generates traffic for landing page matching title . , description for google SEO, blog content around 5000 words with more detailed explanation having 4 to 6 sub-headings and 4 tags. Don't mention PoltryCare ERP anywhere Content should be tone to create more engagement. | M3: https://www.poultry.care/blog/step-by-step-guide-to-managing-diseases-in-contract-broiler-farming-for-reduced-mortality | N3: =CONCATENATE(Instructions!$B$1, " ", Instructions!$B$2, " ", A3, " farmers ", B3, " about ", C3, ". Based on my experiance I suggest ", H3 ," for better guidance. Write a LinkedIn post to highlight ", D3, " to match ", E3, " which generates more engagement and credibility for title ", F3, ". ",Instructions!$B$5, " Create link to url: ",M3 , " Content should be " ,K3, " tone to create more engagement.") -> Consider yourself founder of PoultryCare ERP as Cloud-based ERP solution specific to poultry industry, which serves for all poultry segments like layer, broiler, breeder, broiler integration, hatchery, feedmill and processing plant. As you have experience in both technology and hand-holding exposer with poultry farm owners, use your journey of this into opportunity to address poultry farmer's business needs, pain points and problems through blogs. You play the role of Content marketing head to position PoultryCare ERP using organic content marketing. Contract Broiler Farming/Broiler Integration farmers Fear about High Mortality. Based on my experiance I suggest supervisior should train farmer on Disease and how to be prepared on that sutivation for better guidance. Write a LinkedIn post to highlight Contract Broiler Farming Disease Management to match Contract Broiler Farming Disease symptoms and treatments which generates more engagement and credibility for title . LinkedIn post as conversational format as Hook/question, insightful problem statement, solution for the problem, call-to-action for engagement. Dont include section titles in the content. All within maximum 300 words. Mention PoltryCare if possible in the content, also suggest 4 hashtags addition to #poultrycare each hash tag in small character Create link to url: https://www.poultry.care/blog/step-by-step-guide-to-managing-diseases-in-contract-broiler-farming-for-reduced-mortality Content should be tone to create more engagement. | O3: =CONCATENATE(Instructions!$B$1, " ", Instructions!$B$2, " ", A3, " farmers ", B3, " about ", C3, ". Based on my experiance I suggest ", H3 ," for better guidance. Write a Facebook post to highlight ", D3, " to match ", E3, " which generates more engagement and credibility for title ", F3, ". ",Instructions!$B$7, " Create link to url: ",M3 , " Content should be " ,K3, " tone to create more engagement.") -> Consider yourself founder of PoultryCare ERP as Cloud-based ERP solution specific to poultry industry, which serves for all poultry segments like layer, broiler, breeder, broiler integration, hatchery, feedmill and processing plant. As you have experience in both technology and hand-holding exposer with poultry farm owners, use your journey of this into opportunity to address poultry farmer's business needs, pain points and problems through blogs. You play the role of Content marketing head to position PoultryCare ERP using organic content marketing. Contract Broiler Farming/Broiler Integration farmers Fear about High Mortality. Based on my experiance I suggest supervisior should train farmer on Disease and how to be prepared on that sutivation for better guidance. Write a Facebook post to highlight Contract Broiler Farming Disease Management to match Contract Broiler Farming Disease symptoms and treatments which generates more engagement and credibility for title . Facebook post as conversational format as Hook/question, insightful problem statement, solution for the problem, call-to-action for engagement. Dont include section titles in the content. All within maximum 300 words. Mention PoltryCare if possible in the content, also suggest 4 hashtags addition to #poultrycare each hash tag in small character Create link to url: https://www.poultry.care/blog/step-by-step-guide-to-managing-diseases-in-contract-broiler-farming-for-reduced-mortality Content should be tone to create more engagement. | P3: =CONCATENATE(Instructions!$B$1, " ", Instructions!$B$2, " ", A3, " farmers ", B3, " about ", C3, ". Based on my experiance I suggest ", H3 ," for better guidance. Write a Instagram post to highlight ", D3, " to match ", E3, " which generates more engagement and credibility for title ", F3, ". ",Instructions!$B$6, " Create link to url: ",M3 , " Content should be " ,K3, " tone to create more engagement.") -> Consider yourself founder of PoultryCare ERP as Cloud-based ERP solution specific to poultry industry, which serves for all poultry segments like layer, broiler, breeder, broiler integration, hatchery, feedmill and processing plant. As you have experience in both technology and hand-holding exposer with poultry farm owners, use your journey of this into opportunity to address poultry farmer's business needs, pain points and problems through blogs. You play the role of Content marketing head to position PoultryCare ERP using organic content marketing. Contract Broiler Farming/Broiler Integration farmers Fear about High Mortality. Based on my experiance I suggest supervisior should train farmer on Disease and how to be prepared on that sutivation for better guidance. Write a Instagram post to highlight Contract Broiler Farming Disease Management to match Contract Broiler Farming Disease symptoms and treatments which generates more engagement and credibility for title . Instagram post as conversational format as Hook/question, insightful problem statement, solution for the problem, call-to-action for engagement. Dont include section titles in the content. All within maximum 300 words. Mention PoltryCare if possible in the content, also suggest 4 hashtags addition to #poultrycare each hash tag in small character Create link to url: https://www.poultry.care/blog/step-by-step-guide-to-managing-diseases-in-contract-broiler-farming-for-reduced-mortality Content should be tone to create more engagement. | Q3: =CONCATENATE(Instructions!$B$1, " ", Instructions!$B$2, " ", A3, " farmers ", B3, " about ", C3, ". Based on my experiance I suggest ", H3 ," for better guidance. Write a twitter post to highlight ", D3, " to match ", E3, " which generates more engagement and credibility for title ", F3, ". ",Instructions!$B$8, " Create link to url: ",M3 , " Content should be " ,K3, " tone to create more engagement.") -> Consider yourself founder of PoultryCare ERP as Cloud-based ERP solution specific to poultry industry, which serves for all poultry segments like layer, broiler, breeder, broiler integration, hatchery, feedmill and processing plant. As you have experience in both technology and hand-holding exposer with poultry farm owners, use your journey of this into opportunity to address poultry farmer's business needs, pain points and problems through blogs. You play the role of Content marketing head to position PoultryCare ERP using organic content marketing. Contract Broiler Farming/Broiler Integration farmers Fear about High Mortality. Based on my experiance I suggest supervisior should train farmer on Disease and how to be prepared on that sutivation for better guidance. Write a twitter post to highlight Contract Broiler Farming Disease Management to match Contract Broiler Farming Disease symptoms and treatments which generates more engagement and credibility for title . Twitter post as conversational format as Hook/question, insightful problem statement, solution for the problem, call-to-action for engagement. Dont include section titles in the content. All within maximum 100 words. Mention PoltryCare if possible in the content, also suggest 4 hashtags addition to #poultrycare each hash tag in small character Create link to url: https://www.poultry.care/blog/step-by-step-guide-to-managing-diseases-in-contract-broiler-farming-for-reduced-mortality Content should be tone to create more engagement. | R3: =CONCATENATE("Consider yourself founder of PoultryCare ERP as Cloud-based ERP solution specific to poultry industry, which serves for all poultry segments like layer, broiler, breeder, broiler integration, hatchery, feedmill and processing plant. As you have experience"&" in both technology and hand-holding exposer with poultry farm owners, use your journey of this into opportunity to address poultry farmer's business needs, pain points and problems through blogs. You play the role of Content marketing head to position Po"&"ultryCare ERP using organic content marketing. Contract Broiler Farming/Broiler Integration Farmers ",B3," about ",C3,". Based on my experience I suggest ",H3,". Create script for www.narakeet.com to develop reals and shots video to highlight ",D3," to match ",E3," which generates traffic for landing page matching title. Template for video script for 30 sec, should be start with hook, highlight problem statement, give solution as pointer, end with punch. Add call to action to request PoultryCare subscription for si"&"milar tips and guides Content should be a friendly tone to create more subscribers") -> Consider yourself founder of PoultryCare ERP as Cloud-based ERP solution specific to poultry industry, which serves for all poultry segments like layer, broiler, breeder, broiler integration, hatchery, feedmill and processing plant. As you have experience in both technology and hand-holding exposer with poultry farm owners, use your journey of this into opportunity to address poultry farmer's business needs, pain points and problems through blogs. You play the role of Content marketing head to position PoultryCare ERP using organic content marketing. Contract Broiler Farming/Broiler Integration Farmers Fear about High Mortality. Based on my experience I suggest supervisior should train farmer on Disease and how to be prepared on that sutivation . Create script for www.narakeet.com to develop reals and shots video to highlight Contract Broiler Farming Disease Management to match Contract Broiler Farming Disease symptoms and treatments which generates traffic for landing page matching title. Template for video script for 30 sec, should be start with hook, highlight problem statement, give solution as pointer, end with punch. Add call to action to request PoultryCare subscription for similar tips and guides Content should be a friendly tone to create more subscribers
A4: Contract Broiler Farming/Broiler Integration | B4: Fear | C4: High Mortality | D4: Air Pollution in Broiler Farms | E4: environmental impact of Contract Broiler Farming | G4: avoid air polution in Contract Broiler Farming Farm | H4: supervisior should train farmer on Air Polution and how to be prepared on that sutivation | I4: 45250 | J4: UNDERSTANDING AND MITIGATING AIR POLLUTION IN CONTRACT BROILER FARMING | L4: =CONCATENATE(Instructions!$B$1, " ", Instructions!$B$2, " ", A4, " farmers ", B4, " about ", C4, ". Based on my experiance I suggest ", H4 ," for better guidance. Write a blog to highlight ", D4, " to match ", E4, " which generates traffic for landing page matching title ", F4, ". ",Instructions!$B$4, " Content should be " ,K4, " tone to create more engagement.") -> Consider yourself founder of PoultryCare ERP as Cloud-based ERP solution specific to poultry industry, which serves for all poultry segments like layer, broiler, breeder, broiler integration, hatchery, feedmill and processing plant. As you have experience in both technology and hand-holding exposer with poultry farm owners, use your journey of this into opportunity to address poultry farmer's business needs, pain points and problems through blogs. You play the role of Content marketing head to position PoultryCare ERP using organic content marketing. Contract Broiler Farming/Broiler Integration farmers Fear about High Mortality. Based on my experiance I suggest supervisior should train farmer on Air Polution and how to be prepared on that sutivation for better guidance. Write a blog to highlight Air Pollution in Broiler Farms to match environmental impact of Contract Broiler Farming which generates traffic for landing page matching title . , description for google SEO, blog content around 5000 words with more detailed explanation having 4 to 6 sub-headings and 4 tags. Don't mention PoltryCare ERP anywhere Content should be tone to create more engagement. | M4: https://www.poultry.care/blog/understanding-and-mitigating-air-pollution-in-contract-broiler-farming | N4: =CONCATENATE(Instructions!$B$1, " ", Instructions!$B$2, " ", A4, " farmers ", B4, " about ", C4, ". Based on my experiance I suggest ", H4 ," for better guidance. Write a LinkedIn post to highlight ", D4, " to match ", E4, " which generates more engagement and credibility for title ", F4, ". ",Instructions!$B$5, " Create link to url: ",M4 , " Content should be " ,K4, " tone to create more engagement.") -> Consider yourself founder of PoultryCare ERP as Cloud-based ERP solution specific to poultry industry, which serves for all poultry segments like layer, broiler, breeder, broiler integration, hatchery, feedmill and processing plant. As you have experience in both technology and hand-holding exposer with poultry farm owners, use your journey of this into opportunity to address poultry farmer's business needs, pain points and problems through blogs. You play the role of Content marketing head to position PoultryCare ERP using organic content marketing. Contract Broiler Farming/Broiler Integration farmers Fear about High Mortality. Based on my experiance I suggest supervisior should train farmer on Air Polution and how to be prepared on that sutivation for better guidance. Write a LinkedIn post to highlight Air Pollution in Broiler Farms to match environmental impact of Contract Broiler Farming which generates more engagement and credibility for title . LinkedIn post as conversational format as Hook/question, insightful problem statement, solution for the problem, call-to-action for engagement. Dont include section titles in the content. All within maximum 300 words. Mention PoltryCare if possible in the content, also suggest 4 hashtags addition to #poultrycare each hash tag in small character Create link to url: https://www.poultry.care/blog/understanding-and-mitigating-air-pollution-in-contract-broiler-farming Content should be tone to create more engagement. | O4: =CONCATENATE(Instructions!$B$1, " ", Instructions!$B$2, " ", A4, " farmers ", B4, " about ", C4, ". Based on my experiance I suggest ", H4 ," for better guidance. Write a Facebook post to highlight ", D4, " to match ", E4, " which generates more engagement and credibility for title ", F4, ". ",Instructions!$B$7, " Create link to url: ",M4 , " Content should be " ,K4, " tone to create more engagement.") -> Consider yourself founder of PoultryCare ERP as Cloud-based ERP solution specific to poultry industry, which serves for all poultry segments like layer, broiler, breeder, broiler integration, hatchery, feedmill and processing plant. As you have experience in both technology and hand-holding exposer with poultry farm owners, use your journey of this into opportunity to address poultry farmer's business needs, pain points and problems through blogs. You play the role of Content marketing head to position PoultryCare ERP using organic content marketing. Contract Broiler Farming/Broiler Integration farmers Fear about High Mortality. Based on my experiance I suggest supervisior should train farmer on Air Polution and how to be prepared on that sutivation for better guidance. Write a Facebook post to highlight Air Pollution in Broiler Farms to match environmental impact of Contract Broiler Farming which generates more engagement and credibility for title . Facebook post as conversational format as Hook/question, insightful problem statement, solution for the problem, call-to-action for engagement. Dont include section titles in the content. All within maximum 300 words. Mention PoltryCare if possible in the content, also suggest 4 hashtags addition to #poultrycare each hash tag in small character Create link to url: https://www.poultry.care/blog/understanding-and-mitigating-air-pollution-in-contract-broiler-farming Content should be tone to create more engagement. | P4: =CONCATENATE(Instructions!$B$1, " ", Instructions!$B$2, " ", A4, " farmers ", B4, " about ", C4, ". Based on my experiance I suggest ", H4 ," for better guidance. Write a Instagram post to highlight ", D4, " to match ", E4, " which generates more engagement and credibility for title ", F4, ". ",Instructions!$B$6, " Create link to url: ",M4 , " Content should be " ,K4, " tone to create more engagement.") -> Consider yourself founder of PoultryCare ERP as Cloud-based ERP solution specific to poultry industry, which serves for all poultry segments like layer, broiler, breeder, broiler integration, hatchery, feedmill and processing plant. As you have experience in both technology and hand-holding exposer with poultry farm owners, use your journey of this into opportunity to address poultry farmer's business needs, pain points and problems through blogs. You play the role of Content marketing head to position PoultryCare ERP using organic content marketing. Contract Broiler Farming/Broiler Integration farmers Fear about High Mortality. Based on my experiance I suggest supervisior should train farmer on Air Polution and how to be prepared on that sutivation for better guidance. Write a Instagram post to highlight Air Pollution in Broiler Farms to match environmental impact of Contract Broiler Farming which generates more engagement and credibility for title . Instagram post as conversational format as Hook/question, insightful problem statement, solution for the problem, call-to-action for engagement. Dont include section titles in the content. All within maximum 300 words. Mention PoltryCare if possible in the content, also suggest 4 hashtags addition to #poultrycare each hash tag in small character Create link to url: https://www.poultry.care/blog/understanding-and-mitigating-air-pollution-in-contract-broiler-farming Content should be tone to create more engagement. | Q4: =CONCATENATE(Instructions!$B$1, " ", Instructions!$B$2, " ", A4, " farmers ", B4, " about ", C4, ". Based on my experiance I suggest ", H4 ," for better guidance. Write a twitter post to highlight ", D4, " to match ", E4, " which generates more engagement and credibility for title ", F4, ". ",Instructions!$B$8, " Create link to url: ",M4 , " Content should be " ,K4, " tone to create more engagement.") -> Consider yourself founder of PoultryCare ERP as Cloud-based ERP solution specific to poultry industry, which serves for all poultry segments like layer, broiler, breeder, broiler integration, hatchery, feedmill and processing plant. As you have experience in both technology and hand-holding exposer with poultry farm owners, use your journey of this into opportunity to address poultry farmer's business needs, pain points and problems through blogs. You play the role of Content marketing head to position PoultryCare ERP using organic content marketing. Contract Broiler Farming/Broiler Integration farmers Fear about High Mortality. Based on my experiance I suggest supervisior should train farmer on Air Polution and how to be prepared on that sutivation for better guidance. Write a twitter post to highlight Air Pollution in Broiler Farms to match environmental impact of Contract Broiler Farming which generates more engagement and credibility for title . Twitter post as conversational format as Hook/question, insightful problem statement, solution for the problem, call-to-action for engagement. Dont include section titles in the content. All within maximum 100 words. Mention PoltryCare if possible in the content, also suggest 4 hashtags addition to #poultrycare each hash tag in small character Create link to url: https://www.poultry.care/blog/understanding-and-mitigating-air-pollution-in-contract-broiler-farming Content should be tone to create more engagement. | R4: =CONCATENATE("Consider yourself founder of PoultryCare ERP as Cloud-based ERP solution specific to poultry industry, which serves for all poultry segments like layer, broiler, breeder, broiler integration, hatchery, feedmill and processing plant. As you have experience"&" in both technology and hand-holding exposer with poultry farm owners, use your journey of this into opportunity to address poultry farmer's business needs, pain points and problems through blogs. You play the role of Content marketing head to position Po"&"ultryCare ERP using organic content marketing. Contract Broiler Farming/Broiler Integration Farmers ",B4," about ",C4,". Based on my experience I suggest ",H4,". Create script for www.narakeet.com to develop reals and shots video to highlight ",D4," to match ",E4," which generates traffic for landing page matching title. Template for video script for 30 sec, should be start with hook, highlight problem statement, give solution as pointer, end with punch. Add call to action to request PoultryCare subscription for si"&"milar tips and guides Content should be a friendly tone to create more subscribers") -> Consider yourself founder of PoultryCare ERP as Cloud-based ERP solution specific to poultry industry, which serves for all poultry segments like layer, broiler, breeder, broiler integration, hatchery, feedmill and processing plant. As you have experience in both technology and hand-holding exposer with poultry farm owners, use your journey of this into opportunity to address poultry farmer's business needs, pain points and problems through blogs. You play the role of Content marketing head to position PoultryCare ERP using organic content marketing. Contract Broiler Farming/Broiler Integration Farmers Fear about High Mortality. Based on my experience I suggest supervisior should train farmer on Air Polution and how to be prepared on that sutivation . Create script for www.narakeet.com to develop reals and shots video to highlight Air Pollution in Broiler Farms to match environmental impact of Contract Broiler Farming which generates traffic for landing page matching title. Template for video script for 30 sec, should be start with hook, highlight problem statement, give solution as pointer, end with punch. Add call to action to request PoultryCare subscription for similar tips and guides Content should be a friendly tone to create more subscribers | S4: 45355
A5: Contract Broiler Farming/Broiler Integration | B5: Fear | C5: Supply Chain | D5: inventory management | E5: Managing Contract Broiler Farming farm inventory | G5: Stock management | H5: Farmer informed at the stock closing details to the supervisior before 1week before | I5: 45251 | J5: A COMPREHENSIVE GUIDE TO OPTIMIZING INVENTORY MANAGEMENT IN CONTRACT BROILER FARMING | L5: =CONCATENATE(Instructions!$B$1, " ", Instructions!$B$2, " ", A5, " farmers ", B5, " about ", C5, ". Based on my experiance I suggest ", H5 ," for better guidance. Write a blog to highlight ", D5, " to match ", E5, " which generates traffic for landing page matching title ", F5, ". ",Instructions!$B$4, " Content should be " ,K5, " tone to create more engagement.") -> Consider yourself founder of PoultryCare ERP as Cloud-based ERP solution specific to poultry industry, which serves for all poultry segments like layer, broiler, breeder, broiler integration, hatchery, feedmill and processing plant. As you have experience in both technology and hand-holding exposer with poultry farm owners, use your journey of this into opportunity to address poultry farmer's business needs, pain points and problems through blogs. You play the role of Content marketing head to position PoultryCare ERP using organic content marketing. Contract Broiler Farming/Broiler Integration farmers Fear about Supply Chain. Based on my experiance I suggest Farmer informed at the stock closing details to the supervisior before 1week before for better guidance. Write a blog to highlight inventory management to match Managing Contract Broiler Farming farm inventory which generates traffic for landing page matching title . , description for google SEO, blog content around 5000 words with more detailed explanation having 4 to 6 sub-headings and 4 tags. Don't mention PoltryCare ERP anywhere Content should be tone to create more engagement. | M5: https://www.poultry.care/blog/a-comprehensive-guide-to-optimizing-inventory-management-in-contract-broiler-farming | N5: =CONCATENATE(Instructions!$B$1, " ", Instructions!$B$2, " ", A5, " farmers ", B5, " about ", C5, ". Based on my experiance I suggest ", H5 ," for better guidance. Write a LinkedIn post to highlight ", D5, " to match ", E5, " which generates more engagement and credibility for title ", F5, ". ",Instructions!$B$5, " Create link to url: ",M5 , " Content should be " ,K5, " tone to create more engagement.") -> Consider yourself founder of PoultryCare ERP as Cloud-based ERP solution specific to poultry industry, which serves for all poultry segments like layer, broiler, breeder, broiler integration, hatchery, feedmill and processing plant. As you have experience in both technology and hand-holding exposer with poultry farm owners, use your journey of this into opportunity to address poultry farmer's business needs, pain points and problems through blogs. You play the role of Content marketing head to position PoultryCare ERP using organic content marketing. Contract Broiler Farming/Broiler Integration farmers Fear about Supply Chain. Based on my experiance I suggest Farmer informed at the stock closing details to the supervisior before 1week before for better guidance. Write a LinkedIn post to highlight inventory management to match Managing Contract Broiler Farming farm inventory which generates more engagement and credibility for title . LinkedIn post as conversational format as Hook/question, insightful problem statement, solution for the problem, call-to-action for engagement. Dont include section titles in the content. All within maximum 300 words. Mention PoltryCare if possible in the content, also suggest 4 hashtags addition to #poultrycare each hash tag in small character Create link to url: https://www.poultry.care/blog/a-comprehensive-guide-to-optimizing-inventory-management-in-contract-broiler-farming Content should be tone to create more engagement. | O5: =CONCATENATE(Instructions!$B$1, " ", Instructions!$B$2, " ", A5, " farmers ", B5, " about ", C5, ". Based on my experiance I suggest ", H5 ," for better guidance. Write a Facebook post to highlight ", D5, " to match ", E5, " which generates more engagement and credibility for title ", F5, ". ",Instructions!$B$7, " Create link to url: ",M5 , " Content should be " ,K5, " tone to create more engagement.") -> Consider yourself founder of PoultryCare ERP as Cloud-based ERP solution specific to poultry industry, which serves for all poultry segments like layer, broiler, breeder, broiler integration, hatchery, feedmill and processing plant. As you have experience in both technology and hand-holding exposer with poultry farm owners, use your journey of this into opportunity to address poultry farmer's business needs, pain points and problems through blogs. You play the role of Content marketing head to position PoultryCare ERP using organic content marketing. Contract Broiler Farming/Broiler Integration farmers Fear about Supply Chain. Based on my experiance I suggest Farmer informed at the stock closing details to the supervisior before 1week before for better guidance. Write a Facebook post to highlight inventory management to match Managing Contract Broiler Farming farm inventory which generates more engagement and credibility for title . Facebook post as conversational format as Hook/question, insightful problem statement, solution for the problem, call-to-action for engagement. Dont include section titles in the content. All within maximum 300 words. Mention PoltryCare if possible in the content, also suggest 4 hashtags addition to #poultrycare each hash tag in small character Create link to url: https://www.poultry.care/blog/a-comprehensive-guide-to-optimizing-inventory-management-in-contract-broiler-farming Content should be tone to create more engagement. | P5: =CONCATENATE(Instructions!$B$1, " ", Instructions!$B$2, " ", A5, " farmers ", B5, " about ", C5, ". Based on my experiance I suggest ", H5 ," for better guidance. Write a Instagram post to highlight ", D5, " to match ", E5, " which generates more engagement and credibility for title ", F5, ". ",Instructions!$B$6, " Create link to url: ",M5 , " Content should be " ,K5, " tone to create more engagement.") -> Consider yourself founder of PoultryCare ERP as Cloud-based ERP solution specific to poultry industry, which serves for all poultry segments like layer, broiler, breeder, broiler integration, hatchery, feedmill and processing plant. As you have experience in both technology and hand-holding exposer with poultry farm owners, use your journey of this into opportunity to address poultry farmer's business needs, pain points and problems through blogs. You play the role of Content marketing head to position PoultryCare ERP using organic content marketing. Contract Broiler Farming/Broiler Integration farmers Fear about Supply Chain. Based on my experiance I suggest Farmer informed at the stock closing details to the supervisior before 1week before for better guidance. Write a Instagram post to highlight inventory management to match Managing Contract Broiler Farming farm inventory which generates more engagement and credibility for title . Instagram post as conversational format as Hook/question, insightful problem statement, solution for the problem, call-to-action for engagement. Dont include section titles in the content. All within maximum 300 words. Mention PoltryCare if possible in the content, also suggest 4 hashtags addition to #poultrycare each hash tag in small character Create link to url: https://www.poultry.care/blog/a-comprehensive-guide-to-optimizing-inventory-management-in-contract-broiler-farming Content should be tone to create more engagement. | Q5: =CONCATENATE(Instructions!$B$1, " ", Instructions!$B$2, " ", A5, " farmers ", B5, " about ", C5, ". Based on my experiance I suggest ", H5 ," for better guidance. Write a twitter post to highlight ", D5, " to match ", E5, " which generates more engagement and credibility for title ", F5, ". ",Instructions!$B$8, " Create link to url: ",M5 , " Content should be " ,K5, " tone to create more engagement.") -> Consider yourself founder of PoultryCare ERP as Cloud-based ERP solution specific to poultry industry, which serves for all poultry segments like layer, broiler, breeder, broiler integration, hatchery, feedmill and processing plant. As you have experience in both technology and hand-holding exposer with poultry farm owners, use your journey of this into opportunity to address poultry farmer's business needs, pain points and problems through blogs. You play the role of Content marketing head to position PoultryCare ERP using organic content marketing. Contract Broiler Farming/Broiler Integration farmers Fear about Supply Chain. Based on my experiance I suggest Farmer informed at the stock closing details to the supervisior before 1week before for better guidance. Write a twitter post to highlight inventory management to match Managing Contract Broiler Farming farm inventory which generates more engagement and credibility for title . Twitter post as conversational format as Hook/question, insightful problem statement, solution for the problem, call-to-action for engagement. Dont include section titles in the content. All within maximum 100 words. Mention PoltryCare if possible in the content, also suggest 4 hashtags addition to #poultrycare each hash tag in small character Create link to url: https://www.poultry.care/blog/a-comprehensive-guide-to-optimizing-inventory-management-in-contract-broiler-farming Content should be tone to create more engagement. | R5: =CONCATENATE("Consider yourself founder of PoultryCare ERP as Cloud-based ERP solution specific to poultry industry, which serves for all poultry segments like layer, broiler, breeder, broiler integration, hatchery, feedmill and processing plant. As you have experience"&" in both technology and hand-holding exposer with poultry farm owners, use your journey of this into opportunity to address poultry farmer's business needs, pain points and problems through blogs. You play the role of Content marketing head to position Po"&"ultryCare ERP using organic content marketing. Contract Broiler Farming/Broiler Integration Farmers ",B5," about ",C5,". Based on my experience I suggest ",H5,". Create script for www.narakeet.com to develop reals and shots video to highlight ",D5," to match ",E5," which generates traffic for landing page matching title. Template for video script for 30 sec, should be start with hook, highlight problem statement, give solution as pointer, end with punch. Add call to action to request PoultryCare subscription for si"&"milar tips and guides Content should be a friendly tone to create more subscribers") -> Consider yourself founder of PoultryCare ERP as Cloud-based ERP solution specific to poultry industry, which serves for all poultry segments like layer, broiler, breeder, broiler integration, hatchery, feedmill and processing plant. As you have experience in both technology and hand-holding exposer with poultry farm owners, use your journey of this into opportunity to address poultry farmer's business needs, pain points and problems through blogs. You play the role of Content marketing head to position PoultryCare ERP using organic content marketing. Contract Broiler Farming/Broiler Integration Farmers Fear about Supply Chain. Based on my experience I suggest Farmer informed at the stock closing details to the supervisior before 1week before . Create script for www.narakeet.com to develop reals and shots video to highlight inventory management to match Managing Contract Broiler Farming farm inventory which generates traffic for landing page matching title. Template for video script for 30 sec, should be start with hook, highlight problem statement, give solution as pointer, end with punch. Add call to action to request PoultryCare subscription for similar tips and guides Content should be a friendly tone to create more subscribers
A6: Contract Broiler Farming/Broiler Integration | B6: Fear | C6: Supply Chain | D6: Stock Traching | E6: Tracking stock availability | G6: inventory management | H6: Each farm stock availability details Tracking | I6: 45254 | J6: A COMPREHENSIVE GUIDE TO EFFICIENT STOCK TRACKING IN CONTRACT BROILER FARMING | L6: =CONCATENATE(Instructions!$B$1, " ", Instructions!$B$2, " ", A6, " farmers ", B6, " about ", C6, ". Based on my experiance I suggest ", H6 ," for better guidance. Write a blog to highlight ", D6, " to match ", E6, " which generates traffic for landing page matching title ", F6, ". ",Instructions!$B$4, " Content should be " ,K6, " tone to create more engagement.") -> Consider yourself founder of PoultryCare ERP as Cloud-based ERP solution specific to poultry industry, which serves for all poultry segments like layer, broiler, breeder, broiler integration, hatchery, feedmill and processing plant. As you have experience in both technology and hand-holding exposer with poultry farm owners, use your journey of this into opportunity to address poultry farmer's business needs, pain points and problems through blogs. You play the role of Content marketing head to position PoultryCare ERP using organic content marketing. Contract Broiler Farming/Broiler Integration farmers Fear about Supply Chain. Based on my experiance I suggest Each farm stock availability details Tracking for better guidance. Write a blog to highlight Stock Traching to match Tracking stock availability which generates traffic for landing page matching title . , description for google SEO, blog content around 5000 words with more detailed explanation having 4 to 6 sub-headings and 4 tags. Don't mention PoltryCare ERP anywhere Content should be tone to create more engagement. | M6: https://www.poultry.care/blog/a-comprehensive-guide-to-efficient-stock-tracking-in-contract-broiler-farming | N6: =CONCATENATE(Instructions!$B$1, " ", Instructions!$B$2, " ", A6, " farmers ", B6, " about ", C6, ". Based on my experiance I suggest ", H6 ," for better guidance. Write a LinkedIn post to highlight ", D6, " to match ", E6, " which generates more engagement and credibility for title ", F6, ". ",Instructions!$B$5, " Create link to url: ",M6 , " Content should be " ,K6, " tone to create more engagement.") -> Consider yourself founder of PoultryCare ERP as Cloud-based ERP solution specific to poultry industry, which serves for all poultry segments like layer, broiler, breeder, broiler integration, hatchery, feedmill and processing plant. As you have experience in both technology and hand-holding exposer with poultry farm owners, use your journey of this into opportunity to address poultry farmer's business needs, pain points and problems through blogs. You play the role of Content marketing head to position PoultryCare ERP using organic content marketing. Contract Broiler Farming/Broiler Integration farmers Fear about Supply Chain. Based on my experiance I suggest Each farm stock availability details Tracking for better guidance. Write a LinkedIn post to highlight Stock Traching to match Tracking stock availability which generates more engagement and credibility for title . LinkedIn post as conversational format as Hook/question, insightful problem statement, solution for the problem, call-to-action for engagement. Dont include section titles in the content. All within maximum 300 words. Mention PoltryCare if possible in the content, also suggest 4 hashtags addition to #poultrycare each hash tag in small character Create link to url: https://www.poultry.care/blog/a-comprehensive-guide-to-efficient-stock-tracking-in-contract-broiler-farming Content should be tone to create more engagement. | O6: =CONCATENATE(Instructions!$B$1, " ", Instructions!$B$2, " ", A6, " farmers ", B6, " about ", C6, ". Based on my experiance I suggest ", H6 ," for better guidance. Write a Facebook post to highlight ", D6, " to match ", E6, " which generates more engagement and credibility for title ", F6, ". ",Instructions!$B$7, " Create link to url: ",M6 , " Content should be " ,K6, " tone to create more engagement.") -> Consider yourself founder of PoultryCare ERP as Cloud-based ERP solution specific to poultry industry, which serves for all poultry segments like layer, broiler, breeder, broiler integration, hatchery, feedmill and processing plant. As you have experience in both technology and hand-holding exposer with poultry farm owners, use your journey of this into opportunity to address poultry farmer's business needs, pain points and problems through blogs. You play the role of Content marketing head to position PoultryCare ERP using organic content marketing. Contract Broiler Farming/Broiler Integration farmers Fear about Supply Chain. Based on my experiance I suggest Each farm stock availability details Tracking for better guidance. Write a Facebook post to highlight Stock Traching to match Tracking stock availability which generates more engagement and credibility for title . Facebook post as conversational format as Hook/question, insightful problem statement, solution for the problem, call-to-action for engagement. Dont include section titles in the content. All within maximum 300 words. Mention PoltryCare if possible in the content, also suggest 4 hashtags addition to #poultrycare each hash tag in small character Create link to url: https://www.poultry.care/blog/a-comprehensive-guide-to-efficient-stock-tracking-in-contract-broiler-farming Content should be tone to create more engagement. | P6: =CONCATENATE(Instructions!$B$1, " ", Instructions!$B$2, " ", A6, " farmers ", B6, " about ", C6, ". Based on my experiance I suggest ", H6 ," for better guidance. Write a Instagram post to highlight ", D6, " to match ", E6, " which generates more engagement and credibility for title ", F6, ". ",Instructions!$B$6, " Create link to url: ",M6 , " Content should be " ,K6, " tone to create more engagement.") -> Consider yourself founder of PoultryCare ERP as Cloud-based ERP solution specific to poultry industry, which serves for all poultry segments like layer, broiler, breeder, broiler integration, hatchery, feedmill and processing plant. As you have experience in both technology and hand-holding exposer with poultry farm owners, use your journey of this into opportunity to address poultry farmer's business needs, pain points and problems through blogs. You play the role of Content marketing head to position PoultryCare ERP using organic content marketing. Contract Broiler Farming/Broiler Integration farmers Fear about Supply Chain. Based on my experiance I suggest Each farm stock availability details Tracking for better guidance. Write a Instagram post to highlight Stock Traching to match Tracking stock availability which generates more engagement and credibility for title . Instagram post as conversational format as Hook/question, insightful problem statement, solution for the problem, call-to-action for engagement. Dont include section titles in the content. All within maximum 300 words. Mention PoltryCare if possible in the content, also suggest 4 hashtags addition to #poultrycare each hash tag in small character Create link to url: https://www.poultry.care/blog/a-comprehensive-guide-to-efficient-stock-tracking-in-contract-broiler-farming Content should be tone to create more engagement. | Q6: =CONCATENATE(Instructions!$B$1, " ", Instructions!$B$2, " ", A6, " farmers ", B6, " about ", C6, ". Based on my experiance I suggest ", H6 ," for better guidance. Write a twitter post to highlight ", D6, " to match ", E6, " which generates more engagement and credibility for title ", F6, ". ",Instructions!$B$8, " Create link to url: ",M6 , " Content should be " ,K6, " tone to create more engagement.") -> Consider yourself founder of PoultryCare ERP as Cloud-based ERP solution specific to poultry industry, which serves for all poultry segments like layer, broiler, breeder, broiler integration, hatchery, feedmill and processing plant. As you have experience in both technology and hand-holding exposer with poultry farm owners, use your journey of this into opportunity to address poultry farmer's business needs, pain points and problems through blogs. You play the role of Content marketing head to position PoultryCare ERP using organic content marketing. Contract Broiler Farming/Broiler Integration farmers Fear about Supply Chain. Based on my experiance I suggest Each farm stock availability details Tracking for better guidance. Write a twitter post to highlight Stock Traching to match Tracking stock availability which generates more engagement and credibility for title . Twitter post as conversational format as Hook/question, insightful problem statement, solution for the problem, call-to-action for engagement. Dont include section titles in the content. All within maximum 100 words. Mention PoltryCare if possible in the content, also suggest 4 hashtags addition to #poultrycare each hash tag in small character Create link to url: https://www.poultry.care/blog/a-comprehensive-guide-to-efficient-stock-tracking-in-contract-broiler-farming Content should be tone to create more engagement. | R6: =CONCATENATE("Consider yourself founder of PoultryCare ERP as Cloud-based ERP solution specific to poultry industry, which serves for all poultry segments like layer, broiler, breeder, broiler integration, hatchery, feedmill and processing plant. As you have experience"&" in both technology and hand-holding exposer with poultry farm owners, use your journey of this into opportunity to address poultry farmer's business needs, pain points and problems through blogs. You play the role of Content marketing head to position Po"&"ultryCare ERP using organic content marketing. Contract Broiler Farming/Broiler Integration Farmers ",B6," about ",C6,". Based on my experience I suggest ",H6,". Create script for www.narakeet.com to develop reals and shots video to highlight ",D6," to match ",E6," which generates traffic for landing page matching title. Template for video script for 30 sec, should be start with hook, highlight problem statement, give solution as pointer, end with punch. Add call to action to request PoultryCare subscription for si"&"milar tips and guides Content should be a friendly tone to create more subscribers") -> Consider yourself founder of PoultryCare ERP as Cloud-based ERP solution specific to poultry industry, which serves for all poultry segments like layer, broiler, breeder, broiler integration, hatchery, feedmill and processing plant. As you have experience in both technology and hand-holding exposer with poultry farm owners, use your journey of this into opportunity to address poultry farmer's business needs, pain points and problems through blogs. You play the role of Content marketing head to position PoultryCare ERP using organic content marketing. Contract Broiler Farming/Broiler Integration Farmers Fear about Supply Chain. Based on my experience I suggest Each farm stock availability details Tracking . Create script for www.narakeet.com to develop reals and shots video to highlight Stock Traching to match Tracking stock availability which generates traffic for landing page matching title. Template for video script for 30 sec, should be start with hook, highlight problem statement, give solution as pointer, end with punch. Add call to action to request PoultryCare subscription for similar tips and guides Content should be a friendly tone to create more subscribers
A7: Contract Broiler Farming/Broiler Integration | B7: Fear | C7: Supply Chain | D7: transportation delays | E7: how to avoid transpotation delay in Contract Broiler Farming | G7: Transportation Management | H7: Farmer To inform supervisor about stock before 5 days | I7: 45259 | J7: Mastering On-Time Delivery Strategies to Prevent Transportation Delays in Broiler Farming | L7: =CONCATENATE(Instructions!$B$1, " ", Instructions!$B$2, " ", A7, " farmers ", B7, " about ", C7, ". Based on my experiance I suggest ", H7 ," for better guidance. Write a blog to highlight ", D7, " to match ", E7, " which generates traffic for landing page matching title ", F7, ". ",Instructions!$B$4, " Content should be " ,K7, " tone to create more engagement.") -> Consider yourself founder of PoultryCare ERP as Cloud-based ERP solution specific to poultry industry, which serves for all poultry segments like layer, broiler, breeder, broiler integration, hatchery, feedmill and processing plant. As you have experience in both technology and hand-holding exposer with poultry farm owners, use your journey of this into opportunity to address poultry farmer's business needs, pain points and problems through blogs. You play the role of Content marketing head to position PoultryCare ERP using organic content marketing. Contract Broiler Farming/Broiler Integration farmers Fear about Supply Chain. Based on my experiance I suggest Farmer To inform supervisor about stock before 5 days for better guidance. Write a blog to highlight transportation delays to match how to avoid transpotation delay in Contract Broiler Farming which generates traffic for landing page matching title . , description for google SEO, blog content around 5000 words with more detailed explanation having 4 to 6 sub-headings and 4 tags. Don't mention PoltryCare ERP anywhere Content should be tone to create more engagement. | M7: https://www.poultry.care/blog/mastering-on-time-delivery-strategies-to-prevent-transportation-delays-in-broiler-farming | N7: =CONCATENATE(Instructions!$B$1, " ", Instructions!$B$2, " ", A7, " farmers ", B7, " about ", C7, ". Based on my experiance I suggest ", H7 ," for better guidance. Write a LinkedIn post to highlight ", D7, " to match ", E7, " which generates more engagement and credibility for title ", F7, ". ",Instructions!$B$5, " Create link to url: ",M7 , " Content should be " ,K7, " tone to create more engagement.") -> Consider yourself founder of PoultryCare ERP as Cloud-based ERP solution specific to poultry industry, which serves for all poultry segments like layer, broiler, breeder, broiler integration, hatchery, feedmill and processing plant. As you have experience in both technology and hand-holding exposer with poultry farm owners, use your journey of this into opportunity to address poultry farmer's business needs, pain points and problems through blogs. You play the role of Content marketing head to position PoultryCare ERP using organic content marketing. Contract Broiler Farming/Broiler Integration farmers Fear about Supply Chain. Based on my experiance I suggest Farmer To inform supervisor about stock before 5 days for better guidance. Write a LinkedIn post to highlight transportation delays to match how to avoid transpotation delay in Contract Broiler Farming which generates more engagement and credibility for title . LinkedIn post as conversational format as Hook/question, insightful problem statement, solution for the problem, call-to-action for engagement. Dont include section titles in the content. All within maximum 300 words. Mention PoltryCare if possible in the content, also suggest 4 hashtags addition to #poultrycare each hash tag in small character Create link to url: https://www.poultry.care/blog/mastering-on-time-delivery-strategies-to-prevent-transportation-delays-in-broiler-farming Content should be tone to create more engagement. | O7: =CONCATENATE(Instructions!$B$1, " ", Instructions!$B$2, " ", A7, " farmers ", B7, " about ", C7, ". Based on my experiance I suggest ", H7 ," for better guidance. Write a Facebook post to highlight ", D7, " to match ", E7, " which generates more engagement and credibility for title ", F7, ". ",Instructions!$B$7, " Create link to url: ",M7 , " Content should be " ,K7, " tone to create more engagement.") -> Consider yourself founder of PoultryCare ERP as Cloud-based ERP solution specific to poultry industry, which serves for all poultry segments like layer, broiler, breeder, broiler integration, hatchery, feedmill and processing plant. As you have experience in both technology and hand-holding exposer with poultry farm owners, use your journey of this into opportunity to address poultry farmer's business needs, pain points and problems through blogs. You play the role of Content marketing head to position PoultryCare ERP using organic content marketing. Contract Broiler Farming/Broiler Integration farmers Fear about Supply Chain. Based on my experiance I suggest Farmer To inform supervisor about stock before 5 days for better guidance. Write a Facebook post to highlight transportation delays to match how to avoid transpotation delay in Contract Broiler Farming which generates more engagement and credibility for title . Facebook post as conversational format as Hook/question, insightful problem statement, solution for the problem, call-to-action for engagement. Dont include section titles in the content. All within maximum 300 words. Mention PoltryCare if possible in the content, also suggest 4 hashtags addition to #poultrycare each hash tag in small character Create link to url: https://www.poultry.care/blog/mastering-on-time-delivery-strategies-to-prevent-transportation-delays-in-broiler-farming Content should be tone to create more engagement. | P7: =CONCATENATE(Instructions!$B$1, " ", Instructions!$B$2, " ", A7, " farmers ", B7, " about ", C7, ". Based on my experiance I suggest ", H7 ," for better guidance. Write a Instagram post to highlight ", D7, " to match ", E7, " which generates more engagement and credibility for title ", F7, ". ",Instructions!$B$6, " Create link to url: ",M7 , " Content should be " ,K7, " tone to create more engagement.") -> Consider yourself founder of PoultryCare ERP as Cloud-based ERP solution specific to poultry industry, which serves for all poultry segments like layer, broiler, breeder, broiler integration, hatchery, feedmill and processing plant. As you have experience in both technology and hand-holding exposer with poultry farm owners, use your journey of this into opportunity to address poultry farmer's business needs, pain points and problems through blogs. You play the role of Content marketing head to position PoultryCare ERP using organic content marketing. Contract Broiler Farming/Broiler Integration farmers Fear about Supply Chain. Based on my experiance I suggest Farmer To inform supervisor about stock before 5 days for better guidance. Write a Instagram post to highlight transportation delays to match how to avoid transpotation delay in Contract Broiler Farming which generates more engagement and credibility for title . Instagram post as conversational format as Hook/question, insightful problem statement, solution for the problem, call-to-action for engagement. Dont include section titles in the content. All within maximum 300 words. Mention PoltryCare if possible in the content, also suggest 4 hashtags addition to #poultrycare each hash tag in small character Create link to url: https://www.poultry.care/blog/mastering-on-time-delivery-strategies-to-prevent-transportation-delays-in-broiler-farming Content should be tone to create more engagement. | Q7: =CONCATENATE(Instructions!$B$1, " ", Instructions!$B$2, " ", A7, " farmers ", B7, " about ", C7, ". Based on my experiance I suggest ", H7 ," for better guidance. Write a twitter post to highlight ", D7, " to match ", E7, " which generates more engagement and credibility for title ", F7, ". ",Instructions!$B$8, " Create link to url: ",M7 , " Content should be " ,K7, " tone to create more engagement.") -> Consider yourself founder of PoultryCare ERP as Cloud-based ERP solution specific to poultry industry, which serves for all poultry segments like layer, broiler, breeder, broiler integration, hatchery, feedmill and processing plant. As you have experience in both technology and hand-holding exposer with poultry farm owners, use your journey of this into opportunity to address poultry farmer's business needs, pain points and problems through blogs. You play the role of Content marketing head to position PoultryCare ERP using organic content marketing. Contract Broiler Farming/Broiler Integration farmers Fear about Supply Chain. Based on my experiance I suggest Farmer To inform supervisor about stock before 5 days for better guidance. Write a twitter post to highlight transportation delays to match how to avoid transpotation delay in Contract Broiler Farming which generates more engagement and credibility for title . Twitter post as conversational format as Hook/question, insightful problem statement, solution for the problem, call-to-action for engagement. Dont include section titles in the content. All within maximum 100 words. Mention PoltryCare if possible in the content, also suggest 4 hashtags addition to #poultrycare each hash tag in small character Create link to url: https://www.poultry.care/blog/mastering-on-time-delivery-strategies-to-prevent-transportation-delays-in-broiler-farming Content should be tone to create more engagement. | R7: =CONCATENATE("Consider yourself founder of PoultryCare ERP as Cloud-based ERP solution specific to poultry industry, which serves for all poultry segments like layer, broiler, breeder, broiler integration, hatchery, feedmill and processing plant. As you have experience"&" in both technology and hand-holding exposer with poultry farm owners, use your journey of this into opportunity to address poultry farmer's business needs, pain points and problems through blogs. You play the role of Content marketing head to position Po"&"ultryCare ERP using organic content marketing. Contract Broiler Farming/Broiler Integration Farmers ",B7," about ",C7,". Based on my experience I suggest ",H7,". Create script for www.narakeet.com to develop reals and shots video to highlight ",D7," to match ",E7," which generates traffic for landing page matching title. Template for video script for 30 sec, should be start with hook, highlight problem statement, give solution as pointer, end with punch. Add call to action to request PoultryCare subscription for si"&"milar tips and guides Content should be a friendly tone to create more subscribers") -> Consider yourself founder of PoultryCare ERP as Cloud-based ERP solution specific to poultry industry, which serves for all poultry segments like layer, broiler, breeder, broiler integration, hatchery, feedmill and processing plant. As you have experience in both technology and hand-holding exposer with poultry farm owners, use your journey of this into opportunity to address poultry farmer's business needs, pain points and problems through blogs. You play the role of Content marketing head to position PoultryCare ERP using organic content marketing. Contract Broiler Farming/Broiler Integration Farmers Fear about Supply Chain. Based on my experience I suggest Farmer To inform supervisor about stock before 5 days . Create script for www.narakeet.com to develop reals and shots video to highlight transportation delays to match how to avoid transpotation delay in Contract Broiler Farming which generates traffic for landing page matching title. Template for video script for 30 sec, should be start with hook, highlight problem statement, give solution as pointer, end with punch. Add call to action to request PoultryCare subscription for similar tips and guides Content should be a friendly tone to create more subscribers
A8: Contract Broiler Farming/Broiler Integration | B8: Fear | C8: Invesment planning | D8: Farmer score based invesment | E8: Farmers with Score-Based Investment Planning in Contract Broiler Farming | G8: Fearless Investment Planning with Farmer Score in Contract Broiler Farming | H8: Based on farmer score to discussion about birds placements | I8: 45263 | J8: A Deep Dive into Score-Based Investment Planning for Sustainable Growth | L8: =CONCATENATE(Instructions!$B$1, " ", Instructions!$B$2, " ", A8, " farmers ", B8, " about ", C8, ". Based on my experiance I suggest ", H8 ," for better guidance. Write a blog to highlight ", D8, " to match ", E8, " which generates traffic for landing page matching title ", F8, ". ",Instructions!$B$4, " Content should be " ,K8, " tone to create more engagement.") -> Consider yourself founder of PoultryCare ERP as Cloud-based ERP solution specific to poultry industry, which serves for all poultry segments like layer, broiler, breeder, broiler integration, hatchery, feedmill and processing plant. As you have experience in both technology and hand-holding exposer with poultry farm owners, use your journey of this into opportunity to address poultry farmer's business needs, pain points and problems through blogs. You play the role of Content marketing head to position PoultryCare ERP using organic content marketing. Contract Broiler Farming/Broiler Integration farmers Fear about Invesment planning. Based on my experiance I suggest Based on farmer score to discussion about birds placements for better guidance. Write a blog to highlight Farmer score based invesment to match Farmers with Score-Based Investment Planning in Contract Broiler Farming which generates traffic for landing page matching title . , description for google SEO, blog content around 5000 words with more detailed explanation having 4 to 6 sub-headings and 4 tags. Don't mention PoltryCare ERP anywhere Content should be tone to create more engagement. | M8: https://www.poultry.care/blog/a-deep-dive-into-score-based-investment-planning-for-sustainable-growth | N8: =CONCATENATE(Instructions!$B$1, " ", Instructions!$B$2, " ", A8, " farmers ", B8, " about ", C8, ". Based on my experiance I suggest ", H8 ," for better guidance. Write a LinkedIn post to highlight ", D8, " to match ", E8, " which generates more engagement and credibility for title ", F8, ". ",Instructions!$B$5, " Create link to url: ",M8 , " Content should be " ,K8, " tone to create more engagement.") -> Consider yourself founder of PoultryCare ERP as Cloud-based ERP solution specific to poultry industry, which serves for all poultry segments like layer, broiler, breeder, broiler integration, hatchery, feedmill and processing plant. As you have experience in both technology and hand-holding exposer with poultry farm owners, use your journey of this into opportunity to address poultry farmer's business needs, pain points and problems through blogs. You play the role of Content marketing head to position PoultryCare ERP using organic content marketing. Contract Broiler Farming/Broiler Integration farmers Fear about Invesment planning. Based on my experiance I suggest Based on farmer score to discussion about birds placements for better guidance. Write a LinkedIn post to highlight Farmer score based invesment to match Farmers with Score-Based Investment Planning in Contract Broiler Farming which generates more engagement and credibility for title . LinkedIn post as conversational format as Hook/question, insightful problem statement, solution for the problem, call-to-action for engagement. Dont include section titles in the content. All within maximum 300 words. Mention PoltryCare if possible in the content, also suggest 4 hashtags addition to #poultrycare each hash tag in small character Create link to url: https://www.poultry.care/blog/a-deep-dive-into-score-based-investment-planning-for-sustainable-growth Content should be tone to create more engagement. | O8: =CONCATENATE(Instructions!$B$1, " ", Instructions!$B$2, " ", A8, " farmers ", B8, " about ", C8, ". Based on my experiance I suggest ", H8 ," for better guidance. Write a Facebook post to highlight ", D8, " to match ", E8, " which generates more engagement and credibility for title ", F8, ". ",Instructions!$B$7, " Create link to url: ",M8 , " Content should be " ,K8, " tone to create more engagement.") -> Consider yourself founder of PoultryCare ERP as Cloud-based ERP solution specific to poultry industry, which serves for all poultry segments like layer, broiler, breeder, broiler integration, hatchery, feedmill and processing plant. As you have experience in both technology and hand-holding exposer with poultry farm owners, use your journey of this into opportunity to address poultry farmer's business needs, pain points and problems through blogs. You play the role of Content marketing head to position PoultryCare ERP using organic content marketing. Contract Broiler Farming/Broiler Integration farmers Fear about Invesment planning. Based on my experiance I suggest Based on farmer score to discussion about birds placements for better guidance. Write a Facebook post to highlight Farmer score based invesment to match Farmers with Score-Based Investment Planning in Contract Broiler Farming which generates more engagement and credibility for title . Facebook post as conversational format as Hook/question, insightful problem statement, solution for the problem, call-to-action for engagement. Dont include section titles in the content. All within maximum 300 words. Mention PoltryCare if possible in the content, also suggest 4 hashtags addition to #poultrycare each hash tag in small character Create link to url: https://www.poultry.care/blog/a-deep-dive-into-score-based-investment-planning-for-sustainable-growth Content should be tone to create more engagement. | P8: =CONCATENATE(Instructions!$B$1, " ", Instructions!$B$2, " ", A8, " farmers ", B8, " about ", C8, ". Based on my experiance I suggest ", H8 ," for better guidance. Write a Instagram post to highlight ", D8, " to match ", E8, " which generates more engagement and credibility for title ", F8, ". ",Instructions!$B$6, " Create link to url: ",M8 , " Content should be " ,K8, " tone to create more engagement.") -> Consider yourself founder of PoultryCare ERP as Cloud-based ERP solution specific to poultry industry, which serves for all poultry segments like layer, broiler, breeder, broiler integration, hatchery, feedmill and processing plant. As you have experience in both technology and hand-holding exposer with poultry farm owners, use your journey of this into opportunity to address poultry farmer's business needs, pain points and problems through blogs. You play the role of Content marketing head to position PoultryCare ERP using organic content marketing. Contract Broiler Farming/Broiler Integration farmers Fear about Invesment planning. Based on my experiance I suggest Based on farmer score to discussion about birds placements for better guidance. Write a Instagram post to highlight Farmer score based invesment to match Farmers with Score-Based Investment Planning in Contract Broiler Farming which generates more engagement and credibility for title . Instagram post as conversational format as Hook/question, insightful problem statement, solution for the problem, call-to-action for engagement. Dont include section titles in the content. All within maximum 300 words. Mention PoltryCare if possible in the content, also suggest 4 hashtags addition to #poultrycare each hash tag in small character Create link to url: https://www.poultry.care/blog/a-deep-dive-into-score-based-investment-planning-for-sustainable-growth Content should be tone to create more engagement. | Q8: =CONCATENATE(Instructions!$B$1, " ", Instructions!$B$2, " ", A8, " farmers ", B8, " about ", C8, ". Based on my experiance I suggest ", H8 ," for better guidance. Write a twitter post to highlight ", D8, " to match ", E8, " which generates more engagement and credibility for title ", F8, ". ",Instructions!$B$8, " Create link to url: ",M8 , " Content should be " ,K8, " tone to create more engagement.") -> Consider yourself founder of PoultryCare ERP as Cloud-based ERP solution specific to poultry industry, which serves for all poultry segments like layer, broiler, breeder, broiler integration, hatchery, feedmill and processing plant. As you have experience in both technology and hand-holding exposer with poultry farm owners, use your journey of this into opportunity to address poultry farmer's business needs, pain points and problems through blogs. You play the role of Content marketing head to position PoultryCare ERP using organic content marketing. Contract Broiler Farming/Broiler Integration farmers Fear about Invesment planning. Based on my experiance I suggest Based on farmer score to discussion about birds placements for better guidance. Write a twitter post to highlight Farmer score based invesment to match Farmers with Score-Based Investment Planning in Contract Broiler Farming which generates more engagement and credibility for title . Twitter post as conversational format as Hook/question, insightful problem statement, solution for the problem, call-to-action for engagement. Dont include section titles in the content. All within maximum 100 words. Mention PoltryCare if possible in the content, also suggest 4 hashtags addition to #poultrycare each hash tag in small character Create link to url: https://www.poultry.care/blog/a-deep-dive-into-score-based-investment-planning-for-sustainable-growth Content should be tone to create more engagement. | R8: =CONCATENATE("Consider yourself founder of PoultryCare ERP as Cloud-based ERP solution specific to poultry industry, which serves for all poultry segments like layer, broiler, breeder, broiler integration, hatchery, feedmill and processing plant. As you have experience"&" in both technology and hand-holding exposer with poultry farm owners, use your journey of this into opportunity to address poultry farmer's business needs, pain points and problems through blogs. You play the role of Content marketing head to position Po"&"ultryCare ERP using organic content marketing. Contract Broiler Farming/Broiler Integration Farmers ",B8," about ",C8,". Based on my experience I suggest ",H8,". Create script for www.narakeet.com to develop reals and shots video to highlight ",D8," to match ",E8," which generates traffic for landing page matching title. Template for video script for 30 sec, should be start with hook, highlight problem statement, give solution as pointer, end with punch. Add call to action to request PoultryCare subscription for si"&"milar tips and guides Content should be a friendly tone to create more subscribers") -> Consider yourself founder of PoultryCare ERP as Cloud-based ERP solution specific to poultry industry, which serves for all poultry segments like layer, broiler, breeder, broiler integration, hatchery, feedmill and processing plant. As you have experience in both technology and hand-holding exposer with poultry farm owners, use your journey of this into opportunity to address poultry farmer's business needs, pain points and problems through blogs. You play the role of Content marketing head to position PoultryCare ERP using organic content marketing. Contract Broiler Farming/Broiler Integration Farmers Fear about Invesment planning. Based on my experience I suggest Based on farmer score to discussion about birds placements. Create script for www.narakeet.com to develop reals and shots video to highlight Farmer score based invesment to match Farmers with Score-Based Investment Planning in Contract Broiler Farming which generates traffic for landing page matching title. Template for video script for 30 sec, should be start with hook, highlight problem statement, give solution as pointer, end with punch. Add call to action to request PoultryCare subscription for similar tips and guides Content should be a friendly tone to create more subscribers | S8: 45343
